{"version":"1.5","timestamp":1705365431,"count":301,"index":{"":{"key":"","storage_key":"","template":null,"storage_timestamp":1705362558,"children":{"01.home":1705362558,"02.news":1705362558,"03.schedule":1705362558,"04.reports":1705362558,"05.information":1705362558,"06.location":1705362558,"07.joining":1705362558,"08.constitution":1705362558,"content":1705362558,"search":1705362558},"checksum":"cbc6667581bef750823da202ae055f0c"},"01.home":{"key":"home","storage_key":"01.home","template":"default","storage_timestamp":1705362628,"markdown":{"":{"default":1705362628}},"children":{"01._welcome":1705362558,"02._information":1705362558},"checksum":"ddfb53909d297198d81b6a9bf11c9364"},"01.home\/01._welcome":{"key":"home\/_welcome","storage_key":"01.home\/01._welcome","template":"text","storage_timestamp":1705362558,"markdown":{"":{"text":1705362558}},"checksum":"af2f8885aab76e84cbc534a9e8c44068"},"01.home\/02._information":{"key":"home\/_information","storage_key":"01.home\/02._information","template":"features","storage_timestamp":1705362558,"markdown":{"":{"features":1705362558}},"checksum":"828887462a483cb8470ab70628c98277"},"02.news":{"key":"news","storage_key":"02.news","template":"news-front","storage_timestamp":1705362558,"markdown":{"":{"news-front":1705362558}},"children":{"01.2024-Officer-Elections":1705362558,"02.november-2023c4p":1705362558,"03.chapter-officers-for-2023":1705362558,"04.chapter-officers-for-2021":1705362558,"05.Chapter-Officers-for-2020":1705362558,"06.Zolt\u00e1n-D\u00f6rnyei-presentation":1705362558,"07.2017-Year-End-Social":1705362558,"08.Officers-for-2018":1705362558,"09.Change-in-meeting-time-and-venue":1705362558,"10.2016-Annual-General-Meeting-Minutes":1705362558,"11.2016-2017-Chapter-Officer-Election":1705362558,"12.2016-Summer-Social":1705362558,"13.Kitakyushu-JALT-2015-Officer-Election-Report":1705362558,"14.2015-Officer-Elections":1705362558,"15.2015-Annual-General-Meeting-(AGM)-Minutes":1705362558,"16.2015-Summer-Social":1705362558,"17.Call-for-Presentations-neuroELT-Brain-Days-Conference":1705362558,"18.2013-14-Chapter-Committee-Elections":1705362558,"19.Learner-Development-SIG-Grants":1705362558,"20.Schedule-for-2013":1705362558,"21.Kitakyushu-International-Haiku-Event-November-3rd":1705362558,"22.2013-Chapter-Committee-Elections":1705362558,"23.FAB3-First-Annual-Brain-Days":1705362558,"24.February-2012-Meeting---new-venue":1705362558,"25.End-of-Year-Social-Event":1705362558,"26.Chapter-Elections":1705362558,"27.August-and-September":1705362558,"28.September-Special-MASH-ETJ-JALT-Equinox":1705362558,"29.Later-starting-Time":1705362558,"30.2010-Schedule":1705362558},"checksum":"8df35d691bc79231793859284834359b"},"02.news\/01.2024-Officer-Elections":{"key":"news\/2024-officer-elections","storage_key":"02.news\/01.2024-Officer-Elections","template":"news","storage_timestamp":1705365017,"markdown":{"":{"news":1705365017}},"checksum":"343777a15e1e112a678916a2bddee2b8"},"02.news\/02.november-2023c4p":{"key":"news\/november-2023c4p","storage_key":"02.news\/02.november-2023c4p","template":"news","storage_timestamp":1705362558,"markdown":{"":{"news":1705362558}},"checksum":"fb3637c145f86e4fc71a1db9458b66bb"},"02.news\/03.chapter-officers-for-2023":{"key":"news\/chapter-officers-for-2023","storage_key":"02.news\/03.chapter-officers-for-2023","template":"news","storage_timestamp":1705362558,"markdown":{"":{"news":1705362558}},"checksum":"51cf0f188cb7a08206a6d8a4e481086e"},"02.news\/04.chapter-officers-for-2021":{"key":"news\/chapter-officers-for-2021","storage_key":"02.news\/04.chapter-officers-for-2021","template":"news","storage_timestamp":1705362558,"markdown":{"":{"news":1705362558}},"checksum":"951b53d736ecd02042be508975295a45"},"02.news\/05.Chapter-Officers-for-2020":{"key":"news\/chapter-officers-for-2020","storage_key":"02.news\/05.Chapter-Officers-for-2020","template":"news","storage_timestamp":1705362558,"markdown":{"":{"news":1705362558}},"checksum":"c67d1ac223eeee1e4b64f4eb84ed2061"},"02.news\/06.Zolt\u00e1n-D\u00f6rnyei-presentation":{"key":"news\/zolt\u00e1n-d\u00f6rnyei-presentation","storage_key":"02.news\/06.Zolt\u00e1n-D\u00f6rnyei-presentation","template":"news","storage_timestamp":1705362558,"markdown":{"":{"news":1705362558}},"checksum":"7fd00913c09b170cf38e4838f9966583"},"02.news\/07.2017-Year-End-Social":{"key":"news\/2017-year-end-social","storage_key":"02.news\/07.2017-Year-End-Social","template":"news","storage_timestamp":1705362558,"markdown":{"":{"news":1705362558}},"checksum":"f534aae5a359393cfe4b777303698680"},"02.news\/08.Officers-for-2018":{"key":"news\/officers-for-2018","storage_key":"02.news\/08.Officers-for-2018","template":"news","storage_timestamp":1705362558,"markdown":{"":{"news":1705362558}},"checksum":"7919da40c01dcf4ef71b6f2fcd6f3e10"},"02.news\/09.Change-in-meeting-time-and-venue":{"key":"news\/change-in-meeting-time-and-venue","storage_key":"02.news\/09.Change-in-meeting-time-and-venue","template":"news","storage_timestamp":1705362558,"markdown":{"":{"news":1705362558}},"checksum":"48ad5f86b10378972f6ce81a153b4874"},"02.news\/10.2016-Annual-General-Meeting-Minutes":{"key":"news\/2016-annual-general-meeting-minutes","storage_key":"02.news\/10.2016-Annual-General-Meeting-Minutes","template":"news","storage_timestamp":1705362558,"markdown":{"":{"news":1705362558}},"checksum":"a4a54cb38a46945f87cf3ba639ad916b"},"02.news\/11.2016-2017-Chapter-Officer-Election":{"key":"news\/2016-2017-chapter-officer-election","storage_key":"02.news\/11.2016-2017-Chapter-Officer-Election","template":"news","storage_timestamp":1705362558,"markdown":{"":{"news":1705362558}},"checksum":"ef3ba3264709c8e33713d019de669c0b"},"02.news\/12.2016-Summer-Social":{"key":"news\/2016-summer-social","storage_key":"02.news\/12.2016-Summer-Social","template":"news","storage_timestamp":1705362558,"markdown":{"":{"news":1705362558}},"checksum":"dbaea2e1b3e2d341f69194d33a225cd7"},"02.news\/13.Kitakyushu-JALT-2015-Officer-Election-Report":{"key":"news\/kitakyushu-jalt-2015-officer-election-report","storage_key":"02.news\/13.Kitakyushu-JALT-2015-Officer-Election-Report","template":"news","storage_timestamp":1705362558,"markdown":{"":{"news":1705362558}},"checksum":"22121609ff3a8a54b85cfca7cf329870"},"02.news\/14.2015-Officer-Elections":{"key":"news\/2015-officer-elections","storage_key":"02.news\/14.2015-Officer-Elections","template":"news","storage_timestamp":1705362558,"markdown":{"":{"news":1705362558}},"checksum":"7c2bc4cac6a9bb99a5fdc1bec7b043ea"},"02.news\/15.2015-Annual-General-Meeting-(AGM)-Minutes":{"key":"news\/2015-annual-general-meeting-(agm)-minutes","storage_key":"02.news\/15.2015-Annual-General-Meeting-(AGM)-Minutes","template":"news","storage_timestamp":1705362558,"markdown":{"":{"news":1705362558}},"checksum":"289ec521cf043472019275e5ecdcb201"},"02.news\/16.2015-Summer-Social":{"key":"news\/2015-summer-social","storage_key":"02.news\/16.2015-Summer-Social","template":"news","storage_timestamp":1705362558,"markdown":{"":{"news":1705362558}},"checksum":"c5b37259c78b3edc0078ec2c770318d7"},"02.news\/17.Call-for-Presentations-neuroELT-Brain-Days-Conference":{"key":"news\/call-for-presentations-neuroelt-brain-days-conference","storage_key":"02.news\/17.Call-for-Presentations-neuroELT-Brain-Days-Conference","template":"news","storage_timestamp":1705362558,"markdown":{"":{"news":1705362558}},"checksum":"a9deddf76a9879c71a1f44d2206df9ca"},"02.news\/18.2013-14-Chapter-Committee-Elections":{"key":"news\/2013-14-chapter-committee-elections","storage_key":"02.news\/18.2013-14-Chapter-Committee-Elections","template":"news","storage_timestamp":1705362558,"markdown":{"":{"news":1705362558}},"checksum":"0f18cbcc43f9fe5ca2620d71e1689435"},"02.news\/19.Learner-Development-SIG-Grants":{"key":"news\/learner-development-sig-grants","storage_key":"02.news\/19.Learner-Development-SIG-Grants","template":"news","storage_timestamp":1705362558,"markdown":{"":{"news":1705362558}},"checksum":"1c01bf4c30b4e0b4118c0df478c98d92"},"02.news\/20.Schedule-for-2013":{"key":"news\/schedule-for-2013","storage_key":"02.news\/20.Schedule-for-2013","template":"news","storage_timestamp":1705362558,"markdown":{"":{"news":1705362558}},"checksum":"4941477431c1f50aba753088af77ab71"},"02.news\/21.Kitakyushu-International-Haiku-Event-November-3rd":{"key":"news\/kitakyushu-international-haiku-event-november-3rd","storage_key":"02.news\/21.Kitakyushu-International-Haiku-Event-November-3rd","template":"news","storage_timestamp":1705362558,"markdown":{"":{"news":1705362558}},"checksum":"fb33ebc98f9e780d5311b4d2edc86b02"},"02.news\/22.2013-Chapter-Committee-Elections":{"key":"news\/2013-chapter-committee-elections","storage_key":"02.news\/22.2013-Chapter-Committee-Elections","template":"news","storage_timestamp":1705362558,"markdown":{"":{"news":1705362558}},"checksum":"eb2059dd61521e6ce80f7b69df42a20f"},"02.news\/23.FAB3-First-Annual-Brain-Days":{"key":"news\/fab3-first-annual-brain-days","storage_key":"02.news\/23.FAB3-First-Annual-Brain-Days","template":"news","storage_timestamp":1705362558,"markdown":{"":{"news":1705362558}},"checksum":"ff9c83421ad3e0d06c2b5751a655db88"},"02.news\/24.February-2012-Meeting---new-venue":{"key":"news\/february-2012-meeting---new-venue","storage_key":"02.news\/24.February-2012-Meeting---new-venue","template":"news","storage_timestamp":1705362558,"markdown":{"":{"news":1705362558}},"checksum":"d57f2c9bec9f660a9c13b03b1a3749c1"},"02.news\/25.End-of-Year-Social-Event":{"key":"news\/end-of-year-social-event","storage_key":"02.news\/25.End-of-Year-Social-Event","template":"news","storage_timestamp":1705362558,"markdown":{"":{"news":1705362558}},"checksum":"005bae7e88c50c32de55b61723b3f140"},"02.news\/26.Chapter-Elections":{"key":"news\/chapter-elections","storage_key":"02.news\/26.Chapter-Elections","template":"news","storage_timestamp":1705362558,"markdown":{"":{"news":1705362558}},"checksum":"e9b26d79f7acc4e28521e3fdf84cc0c7"},"02.news\/27.August-and-September":{"key":"news\/august-and-september","storage_key":"02.news\/27.August-and-September","template":"news","storage_timestamp":1705362558,"markdown":{"":{"news":1705362558}},"checksum":"658de94fe36d680f612f1f81229dda7d"},"02.news\/28.September-Special-MASH-ETJ-JALT-Equinox":{"key":"news\/september-special-mash-etj-jalt-equinox","storage_key":"02.news\/28.September-Special-MASH-ETJ-JALT-Equinox","template":"news","storage_timestamp":1705362558,"markdown":{"":{"news":1705362558}},"checksum":"65a38008631e0c9f15018e920b91b4cb"},"02.news\/29.Later-starting-Time":{"key":"news\/later-starting-time","storage_key":"02.news\/29.Later-starting-Time","template":"news","storage_timestamp":1705362558,"markdown":{"":{"news":1705362558}},"checksum":"127ca553db6ef7a915dca63d16825f87"},"02.news\/30.2010-Schedule":{"key":"news\/2010-schedule","storage_key":"02.news\/30.2010-Schedule","template":"news","storage_timestamp":1705362558,"markdown":{"":{"news":1705362558}},"checksum":"a26c21d93fcd5dca25a1b34dbb6e3400"},"03.schedule":{"key":"schedule","storage_key":"03.schedule","template":"default","storage_timestamp":1705362558,"markdown":{"":{"default":1705362558}},"children":{"01.upcoming-events":1705362558,"02.archive":1705362558},"checksum":"7ce18de3fa97ba36331800c6785b7f68"},"03.schedule\/01.upcoming-events":{"key":"schedule\/upcoming-events","storage_key":"03.schedule\/01.upcoming-events","template":"default","storage_timestamp":1705362558,"markdown":{"":{"default":1705362558}},"checksum":"48c3b6a2a27d32e28d566d6e5557edb8"},"03.schedule\/02.archive":{"key":"schedule\/archive","storage_key":"03.schedule\/02.archive","template":"default","storage_timestamp":1705362558,"markdown":{"":{"default":1705362558}},"children":{"01.2023-november-11":1705362558,"02.2023-october-21":1705362558,"03.2023-july-08":1705362558,"04.2023-june-17":1705362558,"05.2023-may-20":1705362558,"06.2023-april-08":1705362558,"07.2023-march-11":1705362558,"08.2023-february-11":1705362558,"09.2023-january-21":1705362558,"10.2022-november-05":1705362558,"11.2022-october-15":1705362558,"12.2022-september-10":1705362558,"13.2022-july-16":1705362558,"14.2022-june-12":1705362558,"15.2022-may-14":1705362558,"16.2021-september-11":1705362558,"17.2021-june-19":1705362558,"18.2021-may-08":1705362558,"19.2021-april-10":1705362558,"20.2021-march-13":1705362558,"21.2021-february-13":1705362558,"22.2021-january-16":1705362558,"23.2020-november-14":1705362558,"24.2020-october-10":1705362558,"25.2020-march-21":1705362558,"26.2020-february-08":1705362558,"27.2020-january-19":1705362558,"28.2019-november-09":1705362558,"29.2019-september-14":1705362558,"30.2019-june-08":1705362558,"31.2019-may-11":1705362558,"32.2019-april-13":1705362558,"33.2019-march-16":1705362558,"34.2019-february-09":1705362558,"35.2019-january-19":1705362558,"36.2018-november-10":1705362558,"37.2018-october-13":1705362558,"38.2018-september-08":1705362558,"39.2018-july-14":1705362558,"40.2018-june-16":1705362558,"41.2018-may-12":1705362558,"42.2018-april-14":1705362558,"43.2018-march-10":1705362558,"44.2018-february-10":1705362558,"45.2018-january-13":1705362558,"46.2017-november-11":1705362558,"47.2017-october-14":1705362558,"48.2017-september-09":1705362558,"49.2017-june-10":1705362558,"50.2017-may-13":1705362558,"51.2017-april-08":1705362558,"52.2017-march-11":1705362558,"53.2017-february-11":1705362558,"54.2017-january-14":1705362558,"55.2016-november-12":1705362558,"56.2016-september-10":1705362558,"57.2016-june-11":1705362558,"58.2016-may-14":1705362558,"59.2016-april-09":1705362558,"60.2016-march-12":1705362558,"61.2016-february-13":1705362558,"62.2016-january-09":1705362558,"63.2015-november-14":1705362558,"64.2015-october-10":1705362558,"65.2015-september-12":1705362558,"66.2015-june-13":1705362558,"67.2015-may-09":1705362558,"68.2015-april-11":1705362558,"69.2015-march-14":1705362558,"70.2015-february-14":1705362558,"71.2015-january-10":1705362558,"72.2014-november-08":1705362558,"73.2014-october-11":1705362558,"74.2014-september-13":1705362558,"75.2014-july-19":1705362558,"76.2014-june-14":1705362558,"77.2014-may-24":1705362558,"78.2014-april-12":1705362558,"79.2014-march-08":1705362558,"80.2014-february-08":1705362558,"81.2014-january-11":1705362558,"82.2013-december-07":1705362558,"83.2013-november-09":1705362558,"84.2013-october-12":1705362558,"85.2013-september-14":1705362558,"86.2013-june-08":1705362558,"87.2013-may-11":1705362558,"88.2013-april-13":1705362558,"89.2013-march-09":1705362558,"90.2013-february-09":1705362558,"91.2013-january-12":1705362558,"92.2012-november-10":1705362558,"93.2012-october-06":1705362558,"94.2012-september-08":1705362558,"95.2012-july-14":1705362558,"96.2012-june-09":1705362558,"97.2012-may-12":1705362558,"98.2012-april-14":1705362558,"99.2012-march-10":1705362558,"100.2012-february-11":1705362558,"101.2012-january-14":1705362558,"102.2011-december-10":1705362558,"103.2011-november-26":1705362558,"104.2011-november-12":1705362558,"105.2011-october-08":1705362558,"106.2011-september-10":1705362558,"107.2011-september-02":1705362558,"108.2011-july-09":1705362558,"109.2011-june-11":1705362558,"110.2011-may-14":1705362558,"111.2011-april-09":1705362558,"112.2011-march-12":1705362558,"113.2011-february-12":1705362558,"114.2011-january-08":1705362558,"115.2010-december-11":1705362558,"116.2010-november-13":1705362558,"117.2010-october-09":1705362558,"118.2010-september-23":1705362558,"119.2010-september-11":1705362558,"120.2010-july-10":1705362558,"121.2010-june-12":1705362558,"122.2010-may-08":1705362558,"123.2010-april-10":1705362558,"124.2010-march-13":1705362558,"125.2010-february-13":1705362558,"126.2010-january-09":1705362558,"127.2009-december-12":1705362558,"128.2009-november-19":1705362558,"129.2009-november-14":1705362558,"130.2009-october-10":1705362558,"131.2009-september-26":1705362558,"132.2009-july-11":1705362558,"133.2009-june-13":1705362558,"134.2009-may-09":1705362558,"135.2009-april-11":1705362558,"136.2009-march-14":1705362558,"137.2009-february-14":1705362558,"138.2009-january-10":1705362558,"139.2008-december-13":1705362558,"140.2008-november-06":1705362558,"141.2008-october-11":1705362558,"142.2008-august-09":1705362558,"143.2008-july-12":1705362558},"checksum":"442a77e62fb7b6921bd5491e18e517e5"},"03.schedule\/02.archive\/01.2023-november-11":{"key":"schedule\/archive\/2023-november-11","storage_key":"03.schedule\/02.archive\/01.2023-november-11","template":"item","storage_timestamp":1705362558,"markdown":{"":{"item":1705362558}},"checksum":"e2835b7aed081e90452be60379f9b436"},"03.schedule\/02.archive\/02.2023-october-21":{"key":"schedule\/archive\/2023-october-21","storage_key":"03.schedule\/02.archive\/02.2023-october-21","template":"item","storage_timestamp":1705362558,"markdown":{"":{"item":1705362558}},"checksum":"d12167af5144cf70a00cfa45f9dd5016"},"03.schedule\/02.archive\/03.2023-july-08":{"key":"schedule\/archive\/2023-july-08","storage_key":"03.schedule\/02.archive\/03.2023-july-08","template":"item","storage_timestamp":1705362558,"markdown":{"":{"item":1705362558}},"checksum":"d885d5256aeb1e94b118ea47d788313a"},"03.schedule\/02.archive\/04.2023-june-17":{"key":"schedule\/archive\/2023-june-17","storage_key":"03.schedule\/02.archive\/04.2023-june-17","template":"item","storage_timestamp":1705362558,"markdown":{"":{"item":1705362558}},"checksum":"3b4258d5a9b1f8e4910abb2afe7dea17"},"03.schedule\/02.archive\/05.2023-may-20":{"key":"schedule\/archive\/2023-may-20","storage_key":"03.schedule\/02.archive\/05.2023-may-20","template":"item","storage_timestamp":1705362558,"markdown":{"":{"item":1705362558}},"checksum":"15c2ac46ba0a9e6fdc5287339e859d78"},"03.schedule\/02.archive\/06.2023-april-08":{"key":"schedule\/archive\/2023-april-08","storage_key":"03.schedule\/02.archive\/06.2023-april-08","template":"item","storage_timestamp":1705362558,"markdown":{"":{"item":1705362558}},"checksum":"14d33d2f45a50ea2f388c9bf0d326c17"},"03.schedule\/02.archive\/07.2023-march-11":{"key":"schedule\/archive\/2023-march-11","storage_key":"03.schedule\/02.archive\/07.2023-march-11","template":"item","storage_timestamp":1705362558,"markdown":{"":{"item":1705362558}},"checksum":"3fe5b4316522beabed9ad4a48124af3f"},"03.schedule\/02.archive\/08.2023-february-11":{"key":"schedule\/archive\/2023-february-11","storage_key":"03.schedule\/02.archive\/08.2023-february-11","template":"item","storage_timestamp":1705362558,"markdown":{"":{"item":1705362558}},"checksum":"d3c51b84051e46f1dd42b372f7c2443d"},"03.schedule\/02.archive\/09.2023-january-21":{"key":"schedule\/archive\/2023-january-21","storage_key":"03.schedule\/02.archive\/09.2023-january-21","template":"item","storage_timestamp":1705362558,"markdown":{"":{"item":1705362558}},"checksum":"553c3d94a7d7c6cda9a193eed692d68b"},"03.schedule\/02.archive\/10.2022-november-05":{"key":"schedule\/archive\/2022-november-05","storage_key":"03.schedule\/02.archive\/10.2022-november-05","template":"item","storage_timestamp":1705362558,"markdown":{"":{"item":1705362558}},"checksum":"66be87908eb0f322727151a1c6389db8"},"03.schedule\/02.archive\/11.2022-october-15":{"key":"schedule\/archive\/2022-october-15","storage_key":"03.schedule\/02.archive\/11.2022-october-15","template":"item","storage_timestamp":1705362558,"markdown":{"":{"item":1705362558}},"checksum":"ddfb1ec0e7b9e86ade11e56cee8f2b3c"},"03.schedule\/02.archive\/12.2022-september-10":{"key":"schedule\/archive\/2022-september-10","storage_key":"03.schedule\/02.archive\/12.2022-september-10","template":"item","storage_timestamp":1705362558,"markdown":{"":{"item":1705362558}},"checksum":"af618bc01268e961d133ed1faa45fd3c"},"03.schedule\/02.archive\/13.2022-july-16":{"key":"schedule\/archive\/2022-july-16","storage_key":"03.schedule\/02.archive\/13.2022-july-16","template":"item","storage_timestamp":1705362558,"markdown":{"":{"item":1705362558}},"checksum":"1f13d79298ceb70aaec567d7b333e67e"},"03.schedule\/02.archive\/14.2022-june-12":{"key":"schedule\/archive\/2022-june-12","storage_key":"03.schedule\/02.archive\/14.2022-june-12","template":"item","storage_timestamp":1705362558,"markdown":{"":{"item":1705362558}},"checksum":"b2945e8925013a2078fd48de7c278946"},"03.schedule\/02.archive\/15.2022-may-14":{"key":"schedule\/archive\/2022-may-14","storage_key":"03.schedule\/02.archive\/15.2022-may-14","template":"item","storage_timestamp":1705362558,"markdown":{"":{"item":1705362558}},"checksum":"f2a3e17d5cbf8a268c84c34296fabf54"},"03.schedule\/02.archive\/16.2021-september-11":{"key":"schedule\/archive\/2021-september-11","storage_key":"03.schedule\/02.archive\/16.2021-september-11","template":"item","storage_timestamp":1705362558,"markdown":{"":{"item":1705362558}},"checksum":"3918b6c1c3a17191cce9fbeef5f79a88"},"03.schedule\/02.archive\/17.2021-june-19":{"key":"schedule\/archive\/2021-june-19","storage_key":"03.schedule\/02.archive\/17.2021-june-19","template":"item","storage_timestamp":1705362558,"markdown":{"":{"item":1705362558}},"checksum":"90ae3ddb0511d6542230860ab482bfed"},"03.schedule\/02.archive\/18.2021-may-08":{"key":"schedule\/archive\/2021-may-08","storage_key":"03.schedule\/02.archive\/18.2021-may-08","template":"item","storage_timestamp":1705362558,"markdown":{"":{"item":1705362558}},"checksum":"6aad297e858bd96f825938e96424c618"},"03.schedule\/02.archive\/19.2021-april-10":{"key":"schedule\/archive\/2021-april-10","storage_key":"03.schedule\/02.archive\/19.2021-april-10","template":"item","storage_timestamp":1705362558,"markdown":{"":{"item":1705362558}},"checksum":"bcb30948dbe2c74707a3f0f2b8cd8b3d"},"03.schedule\/02.archive\/20.2021-march-13":{"key":"schedule\/archive\/2021-march-13","storage_key":"03.schedule\/02.archive\/20.2021-march-13","template":"item","storage_timestamp":1705362558,"markdown":{"":{"item":1705362558}},"checksum":"b351f9ca522e73c0fcba0d4dedec528e"},"03.schedule\/02.archive\/21.2021-february-13":{"key":"schedule\/archive\/2021-february-13","storage_key":"03.schedule\/02.archive\/21.2021-february-13","template":"item","storage_timestamp":1705362558,"markdown":{"":{"item":1705362558}},"checksum":"e632bb2d7980cb412133ad41d76257c7"},"03.schedule\/02.archive\/22.2021-january-16":{"key":"schedule\/archive\/2021-january-16","storage_key":"03.schedule\/02.archive\/22.2021-january-16","template":"item","storage_timestamp":1705362558,"markdown":{"":{"item":1705362558}},"checksum":"ee7fcf3b78f4703bfa1adaaf4bb09982"},"03.schedule\/02.archive\/23.2020-november-14":{"key":"schedule\/archive\/2020-november-14","storage_key":"03.schedule\/02.archive\/23.2020-november-14","template":"item","storage_timestamp":1705362558,"markdown":{"":{"item":1705362558}},"checksum":"4bbec5493f351879a503897e5b111e85"},"03.schedule\/02.archive\/24.2020-october-10":{"key":"schedule\/archive\/2020-october-10","storage_key":"03.schedule\/02.archive\/24.2020-october-10","template":"item","storage_timestamp":1705362558,"markdown":{"":{"item":1705362558}},"checksum":"789ac910dcfa1f8da57e55475cfcf997"},"03.schedule\/02.archive\/25.2020-march-21":{"key":"schedule\/archive\/2020-march-21","storage_key":"03.schedule\/02.archive\/25.2020-march-21","template":"item","storage_timestamp":1705362558,"markdown":{"":{"item":1705362558}},"checksum":"58cd7ecb8ae6cddff88a0195109fe096"},"03.schedule\/02.archive\/26.2020-february-08":{"key":"schedule\/archive\/2020-february-08","storage_key":"03.schedule\/02.archive\/26.2020-february-08","template":"item","storage_timestamp":1705362558,"markdown":{"":{"item":1705362558}},"checksum":"329e76590221c703116b815f63448064"},"03.schedule\/02.archive\/27.2020-january-19":{"key":"schedule\/archive\/2020-january-19","storage_key":"03.schedule\/02.archive\/27.2020-january-19","template":"item","storage_timestamp":1705362558,"markdown":{"":{"item":1705362558}},"checksum":"b453e7a3e602a568387e692cde6247d6"},"03.schedule\/02.archive\/28.2019-november-09":{"key":"schedule\/archive\/2019-november-09","storage_key":"03.schedule\/02.archive\/28.2019-november-09","template":"item","storage_timestamp":1705362558,"markdown":{"":{"item":1705362558}},"checksum":"9bbc6d2c2502a3d1ea8cbe84492df818"},"03.schedule\/02.archive\/29.2019-september-14":{"key":"schedule\/archive\/2019-september-14","storage_key":"03.schedule\/02.archive\/29.2019-september-14","template":"item","storage_timestamp":1705362558,"markdown":{"":{"item":1705362558}},"checksum":"140fedda2e6b4e2a71dc3b3eb9ce1914"},"03.schedule\/02.archive\/30.2019-june-08":{"key":"schedule\/archive\/2019-june-08","storage_key":"03.schedule\/02.archive\/30.2019-june-08","template":"item","storage_timestamp":1705362558,"markdown":{"":{"item":1705362558}},"checksum":"eab0d3f9663f63a7a2203a3c5330bdfd"},"03.schedule\/02.archive\/31.2019-may-11":{"key":"schedule\/archive\/2019-may-11","storage_key":"03.schedule\/02.archive\/31.2019-may-11","template":"item","storage_timestamp":1705362558,"markdown":{"":{"item":1705362558}},"checksum":"5e3874c858069704a865254a2eeb32cb"},"03.schedule\/02.archive\/32.2019-april-13":{"key":"schedule\/archive\/2019-april-13","storage_key":"03.schedule\/02.archive\/32.2019-april-13","template":"item","storage_timestamp":1705362558,"markdown":{"":{"item":1705362558}},"checksum":"2817a9c525982eabc7ccaaff12a46829"},"03.schedule\/02.archive\/33.2019-march-16":{"key":"schedule\/archive\/2019-march-16","storage_key":"03.schedule\/02.archive\/33.2019-march-16","template":"item","storage_timestamp":1705362558,"markdown":{"":{"item":1705362558}},"checksum":"bf5a474ba72df4892748adb13cf5e79f"},"03.schedule\/02.archive\/34.2019-february-09":{"key":"schedule\/archive\/2019-february-09","storage_key":"03.schedule\/02.archive\/34.2019-february-09","template":"item","storage_timestamp":1705362558,"markdown":{"":{"item":1705362558}},"checksum":"9ffe0d6a834640483dda35dd54787eeb"},"03.schedule\/02.archive\/35.2019-january-19":{"key":"schedule\/archive\/2019-january-19","storage_key":"03.schedule\/02.archive\/35.2019-january-19","template":"item","storage_timestamp":1705362558,"markdown":{"":{"item":1705362558}},"checksum":"3e0078c57c96874edb37d7e4f78f9fd9"},"03.schedule\/02.archive\/36.2018-november-10":{"key":"schedule\/archive\/2018-november-10","storage_key":"03.schedule\/02.archive\/36.2018-november-10","template":"item","storage_timestamp":1705362558,"markdown":{"":{"item":1705362558}},"checksum":"3a7de119a2d11497806303e8746654fe"},"03.schedule\/02.archive\/37.2018-october-13":{"key":"schedule\/archive\/2018-october-13","storage_key":"03.schedule\/02.archive\/37.2018-october-13","template":"item","storage_timestamp":1705362558,"markdown":{"":{"item":1705362558}},"checksum":"b41f908f64cfa95b52134e4254c9d798"},"03.schedule\/02.archive\/38.2018-september-08":{"key":"schedule\/archive\/2018-september-08","storage_key":"03.schedule\/02.archive\/38.2018-september-08","template":"item","storage_timestamp":1705362558,"markdown":{"":{"item":1705362558}},"checksum":"97ccb6ff6709d6ddae4f5ccfe7d134e1"},"03.schedule\/02.archive\/39.2018-july-14":{"key":"schedule\/archive\/2018-july-14","storage_key":"03.schedule\/02.archive\/39.2018-july-14","template":"item","storage_timestamp":1705362558,"markdown":{"":{"item":1705362558}},"checksum":"36e1a885a889faee7389f8e629bf05f1"},"03.schedule\/02.archive\/40.2018-june-16":{"key":"schedule\/archive\/2018-june-16","storage_key":"03.schedule\/02.archive\/40.2018-june-16","template":"item","storage_timestamp":1705362558,"markdown":{"":{"item":1705362558}},"checksum":"5615db4b670518abbf2cc7ab2e5467ad"},"03.schedule\/02.archive\/41.2018-may-12":{"key":"schedule\/archive\/2018-may-12","storage_key":"03.schedule\/02.archive\/41.2018-may-12","template":"item","storage_timestamp":1705362558,"markdown":{"":{"item":1705362558}},"checksum":"6892d792312822e2ff40989272925dd7"},"03.schedule\/02.archive\/42.2018-april-14":{"key":"schedule\/archive\/2018-april-14","storage_key":"03.schedule\/02.archive\/42.2018-april-14","template":"item","storage_timestamp":1705362558,"markdown":{"":{"item":1705362558}},"checksum":"7a577dfdb7fee75577be4a39a8737d0c"},"03.schedule\/02.archive\/43.2018-march-10":{"key":"schedule\/archive\/2018-march-10","storage_key":"03.schedule\/02.archive\/43.2018-march-10","template":"item","storage_timestamp":1705362558,"markdown":{"":{"item":1705362558}},"checksum":"80f4c99c9036355093cfff5ef4d76e56"},"03.schedule\/02.archive\/44.2018-february-10":{"key":"schedule\/archive\/2018-february-10","storage_key":"03.schedule\/02.archive\/44.2018-february-10","template":"item","storage_timestamp":1705362558,"markdown":{"":{"item":1705362558}},"checksum":"466ee6e1fcf4c5e526d76dbadca8db86"},"03.schedule\/02.archive\/45.2018-january-13":{"key":"schedule\/archive\/2018-january-13","storage_key":"03.schedule\/02.archive\/45.2018-january-13","template":"item","storage_timestamp":1705362558,"markdown":{"":{"item":1705362558}},"checksum":"880776acc3d2a0dc981effe70a807921"},"03.schedule\/02.archive\/46.2017-november-11":{"key":"schedule\/archive\/2017-november-11","storage_key":"03.schedule\/02.archive\/46.2017-november-11","template":"item","storage_timestamp":1705362558,"markdown":{"":{"item":1705362558}},"checksum":"d5150c842431339e5badc4d48415a18e"},"03.schedule\/02.archive\/47.2017-october-14":{"key":"schedule\/archive\/2017-october-14","storage_key":"03.schedule\/02.archive\/47.2017-october-14","template":"item","storage_timestamp":1705362558,"markdown":{"":{"item":1705362558}},"checksum":"cb7d46bbde95bbb9d501969dbdf5c6e8"},"03.schedule\/02.archive\/48.2017-september-09":{"key":"schedule\/archive\/2017-september-09","storage_key":"03.schedule\/02.archive\/48.2017-september-09","template":"item","storage_timestamp":1705362558,"markdown":{"":{"item":1705362558}},"checksum":"ed6e028de412d996da31aabeb4f61435"},"03.schedule\/02.archive\/49.2017-june-10":{"key":"schedule\/archive\/2017-june-10","storage_key":"03.schedule\/02.archive\/49.2017-june-10","template":"item","storage_timestamp":1705362558,"markdown":{"":{"item":1705362558}},"checksum":"e4c1d7a8c48f4092edf429607bf419c9"},"03.schedule\/02.archive\/50.2017-may-13":{"key":"schedule\/archive\/2017-may-13","storage_key":"03.schedule\/02.archive\/50.2017-may-13","template":"item","storage_timestamp":1705362558,"markdown":{"":{"item":1705362558}},"checksum":"b588b5e34d20927c23f954dc72f628de"},"03.schedule\/02.archive\/51.2017-april-08":{"key":"schedule\/archive\/2017-april-08","storage_key":"03.schedule\/02.archive\/51.2017-april-08","template":"item","storage_timestamp":1705362558,"markdown":{"":{"item":1705362558}},"checksum":"7b7e115abd3a224913351239b27d509f"},"03.schedule\/02.archive\/52.2017-march-11":{"key":"schedule\/archive\/2017-march-11","storage_key":"03.schedule\/02.archive\/52.2017-march-11","template":"item","storage_timestamp":1705362558,"markdown":{"":{"item":1705362558}},"checksum":"e6a72692f11c78a685bd2222442b5052"},"03.schedule\/02.archive\/53.2017-february-11":{"key":"schedule\/archive\/2017-february-11","storage_key":"03.schedule\/02.archive\/53.2017-february-11","template":"item","storage_timestamp":1705362558,"markdown":{"":{"item":1705362558}},"checksum":"c772f64a2f740254df9391e2c5072169"},"03.schedule\/02.archive\/54.2017-january-14":{"key":"schedule\/archive\/2017-january-14","storage_key":"03.schedule\/02.archive\/54.2017-january-14","template":"item","storage_timestamp":1705362558,"markdown":{"":{"item":1705362558}},"checksum":"aa75ae01106f69eb07071ed6900e0efe"},"03.schedule\/02.archive\/55.2016-november-12":{"key":"schedule\/archive\/2016-november-12","storage_key":"03.schedule\/02.archive\/55.2016-november-12","template":"item","storage_timestamp":1705362558,"markdown":{"":{"item":1705362558}},"checksum":"87b758ba4b2567d817f94b6515c989fd"},"03.schedule\/02.archive\/56.2016-september-10":{"key":"schedule\/archive\/2016-september-10","storage_key":"03.schedule\/02.archive\/56.2016-september-10","template":"item","storage_timestamp":1705362558,"markdown":{"":{"item":1705362558}},"checksum":"d0ec96093715ecfbb44e46aa41e7095d"},"03.schedule\/02.archive\/57.2016-june-11":{"key":"schedule\/archive\/2016-june-11","storage_key":"03.schedule\/02.archive\/57.2016-june-11","template":"item","storage_timestamp":1705362558,"markdown":{"":{"item":1705362558}},"checksum":"5f80d0e921d019c26ea7e0c65cce9f60"},"03.schedule\/02.archive\/58.2016-may-14":{"key":"schedule\/archive\/2016-may-14","storage_key":"03.schedule\/02.archive\/58.2016-may-14","template":"item","storage_timestamp":1705362558,"markdown":{"":{"item":1705362558}},"checksum":"10897cec699599cb591dfb084dedada1"},"03.schedule\/02.archive\/59.2016-april-09":{"key":"schedule\/archive\/2016-april-09","storage_key":"03.schedule\/02.archive\/59.2016-april-09","template":"item","storage_timestamp":1705362558,"markdown":{"":{"item":1705362558}},"checksum":"c904b3712e1e72d1c56b9b2f331bac03"},"03.schedule\/02.archive\/60.2016-march-12":{"key":"schedule\/archive\/2016-march-12","storage_key":"03.schedule\/02.archive\/60.2016-march-12","template":"item","storage_timestamp":1705362558,"markdown":{"":{"item":1705362558}},"checksum":"0a455300e3b10dcdcec3c2860df3f56c"},"03.schedule\/02.archive\/61.2016-february-13":{"key":"schedule\/archive\/2016-february-13","storage_key":"03.schedule\/02.archive\/61.2016-february-13","template":"item","storage_timestamp":1705362558,"markdown":{"":{"item":1705362558}},"checksum":"8c4d479de62ec2b8ed3af78a2571d94d"},"03.schedule\/02.archive\/62.2016-january-09":{"key":"schedule\/archive\/2016-january-09","storage_key":"03.schedule\/02.archive\/62.2016-january-09","template":"item","storage_timestamp":1705362558,"markdown":{"":{"item":1705362558}},"checksum":"7f59270b4d108f4e328882eec595dd18"},"03.schedule\/02.archive\/63.2015-november-14":{"key":"schedule\/archive\/2015-november-14","storage_key":"03.schedule\/02.archive\/63.2015-november-14","template":"item","storage_timestamp":1705362558,"markdown":{"":{"item":1705362558}},"checksum":"cb7fd745b1e6195695db12ceef908c97"},"03.schedule\/02.archive\/64.2015-october-10":{"key":"schedule\/archive\/2015-october-10","storage_key":"03.schedule\/02.archive\/64.2015-october-10","template":"item","storage_timestamp":1705362558,"markdown":{"":{"item":1705362558}},"checksum":"57a0895b26106a50c7765e0d10e9cea8"},"03.schedule\/02.archive\/65.2015-september-12":{"key":"schedule\/archive\/2015-september-12","storage_key":"03.schedule\/02.archive\/65.2015-september-12","template":"item","storage_timestamp":1705362558,"markdown":{"":{"item":1705362558}},"checksum":"5ef1ca66a4ef2c9cbc8b7a3df4c33cfc"},"03.schedule\/02.archive\/66.2015-june-13":{"key":"schedule\/archive\/2015-june-13","storage_key":"03.schedule\/02.archive\/66.2015-june-13","template":"item","storage_timestamp":1705362558,"markdown":{"":{"item":1705362558}},"checksum":"a4e3ead052f2bc2f4d8635af174079ea"},"03.schedule\/02.archive\/67.2015-may-09":{"key":"schedule\/archive\/2015-may-09","storage_key":"03.schedule\/02.archive\/67.2015-may-09","template":"item","storage_timestamp":1705362558,"markdown":{"":{"item":1705362558}},"checksum":"d614d43847cc6f7c05a429964aa73766"},"03.schedule\/02.archive\/68.2015-april-11":{"key":"schedule\/archive\/2015-april-11","storage_key":"03.schedule\/02.archive\/68.2015-april-11","template":"item","storage_timestamp":1705362558,"markdown":{"":{"item":1705362558}},"checksum":"52108720f4996bf1f2ea10c1aa5a48ed"},"03.schedule\/02.archive\/69.2015-march-14":{"key":"schedule\/archive\/2015-march-14","storage_key":"03.schedule\/02.archive\/69.2015-march-14","template":"item","storage_timestamp":1705362558,"markdown":{"":{"item":1705362558}},"checksum":"ee06c71c982118397da3baf86bc08ac5"},"03.schedule\/02.archive\/70.2015-february-14":{"key":"schedule\/archive\/2015-february-14","storage_key":"03.schedule\/02.archive\/70.2015-february-14","template":"item","storage_timestamp":1705362558,"markdown":{"":{"item":1705362558}},"checksum":"43fb52e0989ee960d88950ca1661b811"},"03.schedule\/02.archive\/71.2015-january-10":{"key":"schedule\/archive\/2015-january-10","storage_key":"03.schedule\/02.archive\/71.2015-january-10","template":"item","storage_timestamp":1705362558,"markdown":{"":{"item":1705362558}},"checksum":"0e4210d251de315bd88b57a02eb69a7d"},"03.schedule\/02.archive\/72.2014-november-08":{"key":"schedule\/archive\/2014-november-08","storage_key":"03.schedule\/02.archive\/72.2014-november-08","template":"item","storage_timestamp":1705362558,"markdown":{"":{"item":1705362558}},"checksum":"636b95fa7ed8aa074f1326637b8f865c"},"03.schedule\/02.archive\/73.2014-october-11":{"key":"schedule\/archive\/2014-october-11","storage_key":"03.schedule\/02.archive\/73.2014-october-11","template":"item","storage_timestamp":1705362558,"markdown":{"":{"item":1705362558}},"checksum":"952a909905ad519c1e8be86ca9148836"},"03.schedule\/02.archive\/74.2014-september-13":{"key":"schedule\/archive\/2014-september-13","storage_key":"03.schedule\/02.archive\/74.2014-september-13","template":"item","storage_timestamp":1705362558,"markdown":{"":{"item":1705362558}},"checksum":"6a5490330963f0e9e56dc5c30f0e1f66"},"03.schedule\/02.archive\/75.2014-july-19":{"key":"schedule\/archive\/2014-july-19","storage_key":"03.schedule\/02.archive\/75.2014-july-19","template":"item","storage_timestamp":1705362558,"markdown":{"":{"item":1705362558}},"checksum":"87a06ce43d11bf8901aa99d0e50dcd6d"},"03.schedule\/02.archive\/76.2014-june-14":{"key":"schedule\/archive\/2014-june-14","storage_key":"03.schedule\/02.archive\/76.2014-june-14","template":"item","storage_timestamp":1705362558,"markdown":{"":{"item":1705362558}},"checksum":"e8d7dcdb6a430e6fa4ea6ced3236b4f3"},"03.schedule\/02.archive\/77.2014-may-24":{"key":"schedule\/archive\/2014-may-24","storage_key":"03.schedule\/02.archive\/77.2014-may-24","template":"item","storage_timestamp":1705362558,"markdown":{"":{"item":1705362558}},"checksum":"c9316d8f05ca42c4ee967d19c52074b2"},"03.schedule\/02.archive\/78.2014-april-12":{"key":"schedule\/archive\/2014-april-12","storage_key":"03.schedule\/02.archive\/78.2014-april-12","template":"item","storage_timestamp":1705362558,"markdown":{"":{"item":1705362558}},"checksum":"8c5233d4a342167dd60751968254d85d"},"03.schedule\/02.archive\/79.2014-march-08":{"key":"schedule\/archive\/2014-march-08","storage_key":"03.schedule\/02.archive\/79.2014-march-08","template":"item","storage_timestamp":1705362558,"markdown":{"":{"item":1705362558}},"checksum":"f27a3f24c8c719e9740a10aeed8bc95d"},"03.schedule\/02.archive\/80.2014-february-08":{"key":"schedule\/archive\/2014-february-08","storage_key":"03.schedule\/02.archive\/80.2014-february-08","template":"item","storage_timestamp":1705362558,"markdown":{"":{"item":1705362558}},"checksum":"4b5b019aa88c31bae5b29f58ec4f7522"},"03.schedule\/02.archive\/81.2014-january-11":{"key":"schedule\/archive\/2014-january-11","storage_key":"03.schedule\/02.archive\/81.2014-january-11","template":"item","storage_timestamp":1705362558,"markdown":{"":{"item":1705362558}},"checksum":"f5cd29f9808a6e3182c1d7d927cd3789"},"03.schedule\/02.archive\/82.2013-december-07":{"key":"schedule\/archive\/2013-december-07","storage_key":"03.schedule\/02.archive\/82.2013-december-07","template":"item","storage_timestamp":1705362558,"markdown":{"":{"item":1705362558}},"checksum":"d3713b33ad408de75fa910f654c9337e"},"03.schedule\/02.archive\/83.2013-november-09":{"key":"schedule\/archive\/2013-november-09","storage_key":"03.schedule\/02.archive\/83.2013-november-09","template":"item","storage_timestamp":1705362558,"markdown":{"":{"item":1705362558}},"checksum":"b34ea1d9051643b432b353005e9eab91"},"03.schedule\/02.archive\/84.2013-october-12":{"key":"schedule\/archive\/2013-october-12","storage_key":"03.schedule\/02.archive\/84.2013-october-12","template":"item","storage_timestamp":1705362558,"markdown":{"":{"item":1705362558}},"checksum":"f1c27858cae1f1f9ad1a6c7f70ad33a6"},"03.schedule\/02.archive\/85.2013-september-14":{"key":"schedule\/archive\/2013-september-14","storage_key":"03.schedule\/02.archive\/85.2013-september-14","template":"item","storage_timestamp":1705362558,"markdown":{"":{"item":1705362558}},"checksum":"9c30652128e5e98dc836e6de9c6b735f"},"03.schedule\/02.archive\/86.2013-june-08":{"key":"schedule\/archive\/2013-june-08","storage_key":"03.schedule\/02.archive\/86.2013-june-08","template":"item","storage_timestamp":1705362558,"markdown":{"":{"item":1705362558}},"checksum":"15d25a9724bf2c0de65136d667afe02f"},"03.schedule\/02.archive\/87.2013-may-11":{"key":"schedule\/archive\/2013-may-11","storage_key":"03.schedule\/02.archive\/87.2013-may-11","template":"item","storage_timestamp":1705362558,"markdown":{"":{"item":1705362558}},"checksum":"5c421e92a1f1315de3ce93e67b913fd8"},"03.schedule\/02.archive\/88.2013-april-13":{"key":"schedule\/archive\/2013-april-13","storage_key":"03.schedule\/02.archive\/88.2013-april-13","template":"item","storage_timestamp":1705362558,"markdown":{"":{"item":1705362558}},"checksum":"3f9cbb45fdb13b6c2a4d6a410a498ef6"},"03.schedule\/02.archive\/89.2013-march-09":{"key":"schedule\/archive\/2013-march-09","storage_key":"03.schedule\/02.archive\/89.2013-march-09","template":"item","storage_timestamp":1705362558,"markdown":{"":{"item":1705362558}},"checksum":"e7a07d46a8571b9ac62bfc795f4891b7"},"03.schedule\/02.archive\/90.2013-february-09":{"key":"schedule\/archive\/2013-february-09","storage_key":"03.schedule\/02.archive\/90.2013-february-09","template":"item","storage_timestamp":1705362558,"markdown":{"":{"item":1705362558}},"checksum":"93a622b37cb8d07ef257a98d09902dcd"},"03.schedule\/02.archive\/91.2013-january-12":{"key":"schedule\/archive\/2013-january-12","storage_key":"03.schedule\/02.archive\/91.2013-january-12","template":"item","storage_timestamp":1705362558,"markdown":{"":{"item":1705362558}},"checksum":"016cac9085edf84821488b019a968051"},"03.schedule\/02.archive\/92.2012-november-10":{"key":"schedule\/archive\/2012-november-10","storage_key":"03.schedule\/02.archive\/92.2012-november-10","template":"item","storage_timestamp":1705362558,"markdown":{"":{"item":1705362558}},"checksum":"def8a4a09782d0a8a9665c2bb1ebcebc"},"03.schedule\/02.archive\/93.2012-october-06":{"key":"schedule\/archive\/2012-october-06","storage_key":"03.schedule\/02.archive\/93.2012-october-06","template":"item","storage_timestamp":1705362558,"markdown":{"":{"item":1705362558}},"checksum":"a0046b6112a39bc5208266ca6bbe8ebd"},"03.schedule\/02.archive\/94.2012-september-08":{"key":"schedule\/archive\/2012-september-08","storage_key":"03.schedule\/02.archive\/94.2012-september-08","template":"item","storage_timestamp":1705362558,"markdown":{"":{"item":1705362558}},"checksum":"823592b56abc0e6b0961433ff1b7a60a"},"03.schedule\/02.archive\/95.2012-july-14":{"key":"schedule\/archive\/2012-july-14","storage_key":"03.schedule\/02.archive\/95.2012-july-14","template":"item","storage_timestamp":1705362558,"markdown":{"":{"item":1705362558}},"checksum":"fac056be23029d423fadd8ae7f5fcea5"},"03.schedule\/02.archive\/96.2012-june-09":{"key":"schedule\/archive\/2012-june-09","storage_key":"03.schedule\/02.archive\/96.2012-june-09","template":"item","storage_timestamp":1705362558,"markdown":{"":{"item":1705362558}},"checksum":"9542b79b699f30905ab7501ffe744e38"},"03.schedule\/02.archive\/97.2012-may-12":{"key":"schedule\/archive\/2012-may-12","storage_key":"03.schedule\/02.archive\/97.2012-may-12","template":"item","storage_timestamp":1705362558,"markdown":{"":{"item":1705362558}},"checksum":"fd1d0cd0ebea06898e5d7a311c3de492"},"03.schedule\/02.archive\/98.2012-april-14":{"key":"schedule\/archive\/2012-april-14","storage_key":"03.schedule\/02.archive\/98.2012-april-14","template":"item","storage_timestamp":1705362558,"markdown":{"":{"item":1705362558}},"checksum":"4e3b1983531c81edbabbbc6ef0164073"},"03.schedule\/02.archive\/99.2012-march-10":{"key":"schedule\/archive\/2012-march-10","storage_key":"03.schedule\/02.archive\/99.2012-march-10","template":"item","storage_timestamp":1705362558,"markdown":{"":{"item":1705362558}},"checksum":"4b1b42a9b78eca70fc6c3d65180f89e0"},"03.schedule\/02.archive\/100.2012-february-11":{"key":"schedule\/archive\/2012-february-11","storage_key":"03.schedule\/02.archive\/100.2012-february-11","template":"item","storage_timestamp":1705362558,"markdown":{"":{"item":1705362558}},"checksum":"d5fcf31d390f11bfacf69916d9342c01"},"03.schedule\/02.archive\/101.2012-january-14":{"key":"schedule\/archive\/2012-january-14","storage_key":"03.schedule\/02.archive\/101.2012-january-14","template":"item","storage_timestamp":1705362558,"markdown":{"":{"item":1705362558}},"checksum":"146d18b3487b0752ffee2c50b1a6da59"},"03.schedule\/02.archive\/102.2011-december-10":{"key":"schedule\/archive\/2011-december-10","storage_key":"03.schedule\/02.archive\/102.2011-december-10","template":"item","storage_timestamp":1705362558,"markdown":{"":{"item":1705362558}},"checksum":"f358eb0766c695fc051918c7630f5bd7"},"03.schedule\/02.archive\/103.2011-november-26":{"key":"schedule\/archive\/2011-november-26","storage_key":"03.schedule\/02.archive\/103.2011-november-26","template":"item","storage_timestamp":1705362558,"markdown":{"":{"item":1705362558}},"checksum":"e1955441c38462dbc8601d2456568e12"},"03.schedule\/02.archive\/104.2011-november-12":{"key":"schedule\/archive\/2011-november-12","storage_key":"03.schedule\/02.archive\/104.2011-november-12","template":"item","storage_timestamp":1705362558,"markdown":{"":{"item":1705362558}},"checksum":"19c31a860e4650b7589feb44ba95145c"},"03.schedule\/02.archive\/105.2011-october-08":{"key":"schedule\/archive\/2011-october-08","storage_key":"03.schedule\/02.archive\/105.2011-october-08","template":"item","storage_timestamp":1705362558,"markdown":{"":{"item":1705362558}},"checksum":"1ea591bc0fde4298fd02b383a7971b65"},"03.schedule\/02.archive\/106.2011-september-10":{"key":"schedule\/archive\/2011-september-10","storage_key":"03.schedule\/02.archive\/106.2011-september-10","template":"item","storage_timestamp":1705362558,"markdown":{"":{"item":1705362558}},"checksum":"648f3f6a627b4b836f1bffe6803c9519"},"03.schedule\/02.archive\/107.2011-september-02":{"key":"schedule\/archive\/2011-september-02","storage_key":"03.schedule\/02.archive\/107.2011-september-02","template":"item","storage_timestamp":1705362558,"markdown":{"":{"item":1705362558}},"checksum":"16b67b6fd04e2e81638b34650ae4f2a5"},"03.schedule\/02.archive\/108.2011-july-09":{"key":"schedule\/archive\/2011-july-09","storage_key":"03.schedule\/02.archive\/108.2011-july-09","template":"item","storage_timestamp":1705362558,"markdown":{"":{"item":1705362558}},"checksum":"5874ab61cdb83151c41a53c1ce2b15c6"},"03.schedule\/02.archive\/109.2011-june-11":{"key":"schedule\/archive\/2011-june-11","storage_key":"03.schedule\/02.archive\/109.2011-june-11","template":"item","storage_timestamp":1705362558,"markdown":{"":{"item":1705362558}},"checksum":"a6332d7974f4f12df74e7531857939dd"},"03.schedule\/02.archive\/110.2011-may-14":{"key":"schedule\/archive\/2011-may-14","storage_key":"03.schedule\/02.archive\/110.2011-may-14","template":"item","storage_timestamp":1705362558,"markdown":{"":{"item":1705362558}},"checksum":"9ada5f987db22ac55299bc780585bcc1"},"03.schedule\/02.archive\/111.2011-april-09":{"key":"schedule\/archive\/2011-april-09","storage_key":"03.schedule\/02.archive\/111.2011-april-09","template":"item","storage_timestamp":1705362558,"markdown":{"":{"item":1705362558}},"checksum":"641ebe08b17e1585ce53e6b8c394d245"},"03.schedule\/02.archive\/112.2011-march-12":{"key":"schedule\/archive\/2011-march-12","storage_key":"03.schedule\/02.archive\/112.2011-march-12","template":"item","storage_timestamp":1705362558,"markdown":{"":{"item":1705362558}},"checksum":"e29d3bf0291f52a55be3cc26ff7568a4"},"03.schedule\/02.archive\/113.2011-february-12":{"key":"schedule\/archive\/2011-february-12","storage_key":"03.schedule\/02.archive\/113.2011-february-12","template":"item","storage_timestamp":1705362558,"markdown":{"":{"item":1705362558}},"checksum":"fd860295a53c0f65414a84b0bf2429c9"},"03.schedule\/02.archive\/114.2011-january-08":{"key":"schedule\/archive\/2011-january-08","storage_key":"03.schedule\/02.archive\/114.2011-january-08","template":"item","storage_timestamp":1705362558,"markdown":{"":{"item":1705362558}},"checksum":"d082f038e53ed5067c0b5dd451bd0148"},"03.schedule\/02.archive\/115.2010-december-11":{"key":"schedule\/archive\/2010-december-11","storage_key":"03.schedule\/02.archive\/115.2010-december-11","template":"item","storage_timestamp":1705362558,"markdown":{"":{"item":1705362558}},"checksum":"456c9577d95f903e69f7116a48074894"},"03.schedule\/02.archive\/116.2010-november-13":{"key":"schedule\/archive\/2010-november-13","storage_key":"03.schedule\/02.archive\/116.2010-november-13","template":"item","storage_timestamp":1705362558,"markdown":{"":{"item":1705362558}},"checksum":"cef7881238e0cf8884312b633e3d7c98"},"03.schedule\/02.archive\/117.2010-october-09":{"key":"schedule\/archive\/2010-october-09","storage_key":"03.schedule\/02.archive\/117.2010-october-09","template":"item","storage_timestamp":1705362558,"markdown":{"":{"item":1705362558}},"checksum":"f6e9a77a5f9d56d8dda500e5b1d719aa"},"03.schedule\/02.archive\/118.2010-september-23":{"key":"schedule\/archive\/2010-september-23","storage_key":"03.schedule\/02.archive\/118.2010-september-23","template":"item","storage_timestamp":1705362558,"markdown":{"":{"item":1705362558}},"checksum":"cbb326f9298d3d324b179cb7ad2043a9"},"03.schedule\/02.archive\/119.2010-september-11":{"key":"schedule\/archive\/2010-september-11","storage_key":"03.schedule\/02.archive\/119.2010-september-11","template":"item","storage_timestamp":1705362558,"markdown":{"":{"item":1705362558}},"checksum":"a02b2cd8f7e0671fc89fa406f9463151"},"03.schedule\/02.archive\/120.2010-july-10":{"key":"schedule\/archive\/2010-july-10","storage_key":"03.schedule\/02.archive\/120.2010-july-10","template":"item","storage_timestamp":1705362558,"markdown":{"":{"item":1705362558}},"checksum":"26511f4a72231a49e11f800419230149"},"03.schedule\/02.archive\/121.2010-june-12":{"key":"schedule\/archive\/2010-june-12","storage_key":"03.schedule\/02.archive\/121.2010-june-12","template":"item","storage_timestamp":1705362558,"markdown":{"":{"item":1705362558}},"checksum":"fe9d30b18cff6a86e27c7f7fcdcbb8bc"},"03.schedule\/02.archive\/122.2010-may-08":{"key":"schedule\/archive\/2010-may-08","storage_key":"03.schedule\/02.archive\/122.2010-may-08","template":"item","storage_timestamp":1705362558,"markdown":{"":{"item":1705362558}},"checksum":"cb6b743f3f577cf955c6106b46e1b504"},"03.schedule\/02.archive\/123.2010-april-10":{"key":"schedule\/archive\/2010-april-10","storage_key":"03.schedule\/02.archive\/123.2010-april-10","template":"item","storage_timestamp":1705362558,"markdown":{"":{"item":1705362558}},"checksum":"8faa2eac98cc06e1f48491593adf7d53"},"03.schedule\/02.archive\/124.2010-march-13":{"key":"schedule\/archive\/2010-march-13","storage_key":"03.schedule\/02.archive\/124.2010-march-13","template":"item","storage_timestamp":1705362558,"markdown":{"":{"item":1705362558}},"checksum":"b882c36d1296d54064bd9cf63e13ba19"},"03.schedule\/02.archive\/125.2010-february-13":{"key":"schedule\/archive\/2010-february-13","storage_key":"03.schedule\/02.archive\/125.2010-february-13","template":"item","storage_timestamp":1705362558,"markdown":{"":{"item":1705362558}},"checksum":"ad600156396cbb47a47ace25897c24de"},"03.schedule\/02.archive\/126.2010-january-09":{"key":"schedule\/archive\/2010-january-09","storage_key":"03.schedule\/02.archive\/126.2010-january-09","template":"item","storage_timestamp":1705362558,"markdown":{"":{"item":1705362558}},"checksum":"f6ec0e88f43f01fd97b96a08edef65b7"},"03.schedule\/02.archive\/127.2009-december-12":{"key":"schedule\/archive\/2009-december-12","storage_key":"03.schedule\/02.archive\/127.2009-december-12","template":"item","storage_timestamp":1705362558,"markdown":{"":{"item":1705362558}},"checksum":"fb549c2ecf03a43c622fb569dbef13d3"},"03.schedule\/02.archive\/128.2009-november-19":{"key":"schedule\/archive\/2009-november-19","storage_key":"03.schedule\/02.archive\/128.2009-november-19","template":"item","storage_timestamp":1705362558,"markdown":{"":{"item":1705362558}},"checksum":"9d973622cfac313c78c00e4f674d66b2"},"03.schedule\/02.archive\/129.2009-november-14":{"key":"schedule\/archive\/2009-november-14","storage_key":"03.schedule\/02.archive\/129.2009-november-14","template":"item","storage_timestamp":1705362558,"markdown":{"":{"item":1705362558}},"checksum":"ede4666edd7be7ba7ebe0f84c55012d2"},"03.schedule\/02.archive\/130.2009-october-10":{"key":"schedule\/archive\/2009-october-10","storage_key":"03.schedule\/02.archive\/130.2009-october-10","template":"item","storage_timestamp":1705362558,"markdown":{"":{"item":1705362558}},"checksum":"8bd1ae39ccc6762f09800b8b38f59c12"},"03.schedule\/02.archive\/131.2009-september-26":{"key":"schedule\/archive\/2009-september-26","storage_key":"03.schedule\/02.archive\/131.2009-september-26","template":"item","storage_timestamp":1705362558,"markdown":{"":{"item":1705362558}},"checksum":"74618739d9c5fb7ff1e1db1187aefc25"},"03.schedule\/02.archive\/132.2009-july-11":{"key":"schedule\/archive\/2009-july-11","storage_key":"03.schedule\/02.archive\/132.2009-july-11","template":"item","storage_timestamp":1705362558,"markdown":{"":{"item":1705362558}},"checksum":"50d510f4106752094e5521d84b10b6b2"},"03.schedule\/02.archive\/133.2009-june-13":{"key":"schedule\/archive\/2009-june-13","storage_key":"03.schedule\/02.archive\/133.2009-june-13","template":"item","storage_timestamp":1705362558,"markdown":{"":{"item":1705362558}},"checksum":"e6dcd019ed48248d0718b0886f5c7d16"},"03.schedule\/02.archive\/134.2009-may-09":{"key":"schedule\/archive\/2009-may-09","storage_key":"03.schedule\/02.archive\/134.2009-may-09","template":"item","storage_timestamp":1705362558,"markdown":{"":{"item":1705362558}},"checksum":"1cf00f5b39156a42d295ce8bab42360e"},"03.schedule\/02.archive\/135.2009-april-11":{"key":"schedule\/archive\/2009-april-11","storage_key":"03.schedule\/02.archive\/135.2009-april-11","template":"item","storage_timestamp":1705362558,"markdown":{"":{"item":1705362558}},"checksum":"2ac64868ebedf06ac64f187edb71721c"},"03.schedule\/02.archive\/136.2009-march-14":{"key":"schedule\/archive\/2009-march-14","storage_key":"03.schedule\/02.archive\/136.2009-march-14","template":"item","storage_timestamp":1705362558,"markdown":{"":{"item":1705362558}},"checksum":"a59ac290998efe5892ee9eaebf89428b"},"03.schedule\/02.archive\/137.2009-february-14":{"key":"schedule\/archive\/2009-february-14","storage_key":"03.schedule\/02.archive\/137.2009-february-14","template":"item","storage_timestamp":1705362558,"markdown":{"":{"item":1705362558}},"checksum":"be52c10abd3658201d138e1f96013302"},"03.schedule\/02.archive\/138.2009-january-10":{"key":"schedule\/archive\/2009-january-10","storage_key":"03.schedule\/02.archive\/138.2009-january-10","template":"item","storage_timestamp":1705362558,"markdown":{"":{"item":1705362558}},"checksum":"9b4f08d0116328b8e75541a08b541ae4"},"03.schedule\/02.archive\/139.2008-december-13":{"key":"schedule\/archive\/2008-december-13","storage_key":"03.schedule\/02.archive\/139.2008-december-13","template":"item","storage_timestamp":1705362558,"markdown":{"":{"item":1705362558}},"checksum":"6abde9451602a2b534fba71cd5dcec19"},"03.schedule\/02.archive\/140.2008-november-06":{"key":"schedule\/archive\/2008-november-06","storage_key":"03.schedule\/02.archive\/140.2008-november-06","template":"item","storage_timestamp":1705362558,"markdown":{"":{"item":1705362558}},"checksum":"cbd85c1d506f86192d90baeae27b04bc"},"03.schedule\/02.archive\/141.2008-october-11":{"key":"schedule\/archive\/2008-october-11","storage_key":"03.schedule\/02.archive\/141.2008-october-11","template":"item","storage_timestamp":1705362558,"markdown":{"":{"item":1705362558}},"checksum":"3454526cacdbb7b2a3d5e21874843187"},"03.schedule\/02.archive\/142.2008-august-09":{"key":"schedule\/archive\/2008-august-09","storage_key":"03.schedule\/02.archive\/142.2008-august-09","template":"item","storage_timestamp":1705362558,"markdown":{"":{"item":1705362558}},"checksum":"40c522579a92049a7f4c11a4e3589050"},"03.schedule\/02.archive\/143.2008-july-12":{"key":"schedule\/archive\/2008-july-12","storage_key":"03.schedule\/02.archive\/143.2008-july-12","template":"item","storage_timestamp":1705362558,"markdown":{"":{"item":1705362558}},"checksum":"b03f6ac9e64d95205889249631738e6a"},"04.reports":{"key":"reports","storage_key":"04.reports","template":"reports-front","storage_timestamp":1705365431,"markdown":{"":{"reports-front":1705365431}},"children":{"01.2021-09-11":1705362558,"02.2021-06-19":1705362558,"03.2021-05-08":1705362558,"04.2021-04-10":1705362558,"05.2021-03-13":1705362558,"06.2021-02-13":1705362558,"07.2021-01-16":1705362558,"08.2020-02-08":1705362558,"09.2020-01-19":1705362558,"10.2019-11-09":1705362558,"11.2019-09-14":1705362558,"12.2019-06-08":1705362558,"13.2019-05-11":1705362558,"14.2019-04-13":1705362558,"15.2019-03-16":1705362558,"16.2019-02-09":1705362558,"17.2019-01-19":1705362558,"18.2018-05-12":1705362558,"19.2018-04-14":1705362558,"20.2018-02-10":1705362558,"21.2018-01-13":1705362558,"22.2018-03-10":1705362558,"23.2017-11-11":1705362558,"24.2017-10-14":1705362558,"25.2017-09-09":1705362558,"26.2017-06-10":1705362558,"27.2017-05-13":1705362558,"28.2017-04-08":1705362558,"29.2017-02-11":1705362558,"30.2017-01-14":1705362558,"31.2016-11-12":1705362558,"32.2016-10-08":1705362558,"33.2016-09-10":1705362558,"34.2016-06-11":1705362558,"35.2016-05-14":1705362558,"36.2016-04-09":1705362558,"37.2016-03-12":1705362558,"38.2016-02-13":1705362558,"39.2016-01-09":1705362558,"40.2015-11-14":1705362558,"41.2015-10-10":1705362558,"42.2015-09-12":1705362558,"43.2015-06-13":1705362558,"44.2015-05-09":1705362558,"45.2015-04-11":1705362558,"46.2015-03-14":1705362558,"47.2015-02-14":1705362558,"48.2015-01-10":1705362558,"49.2014-11-08":1705362558,"50.2014-10-11":1705362558,"51.2014-09-13":1705362558,"52.2014-07-19":1705362558,"53.2014-06-14":1705362558,"54.2014-05-24":1705362558,"55.2014-03-08":1705362558,"56.2014-01-11":1705362558,"57.2013-09-14":1705362558,"58.2013-05-11":1705362558,"59.2013-06-08":1705362558,"60.2013-04-13":1705362558,"61.2013-03-09":1705362558,"62.2013-02-09":1705362558,"63.2013-01-12":1705362558,"64.2012-11-10":1705362558,"65.2012-10-06":1705362558,"66.2012-09-08":1705362558,"67.2012-07-14":1705362558,"68.2012-06-09":1705362558,"69.2012-05-12":1705362558,"70.2012-04-14":1705362558,"71.2012-03-10":1705362558,"72.2012-02-11":1705362558,"73.2012-01-14":1705362558,"74.2011-11-26":1705362558,"75.2011-11-12":1705362558,"76.2011-10-08":1705362558,"77.2011-09-10":1705362558,"78.2011-09-03":1705362558,"79.2011-07-09":1705362558,"80.2011-06-11":1705362558,"81.2011-05-14":1705362558,"82.2011-04-09":1705362558,"83.2011-03-12":1705362558,"84.2011-02-12":1705362558,"85.2011-01-08":1705362558,"86.2010-11-13":1705362558,"87.2010-10-09":1705362558,"88.2010-09-23":1705362558,"89.2010-09-11":1705362558,"90.2010-07-10":1705362558,"91.2010-06-12":1705362558,"92.2010-05-08":1705362558,"93.2010-04-10":1705362558,"94.2010-03-13":1705362558,"95.2010-02-13":1705362558,"96.2010-01-09":1705362558,"97.2009-11-19":1705362558,"98.2009-11-15":1705362558,"99.2009-10-10":1705362558,"100.2009-09-26":1705362558,"101.2009-07-11":1705362558,"102.2009-06-13":1705362558,"103.2009-05-09":1705362558,"104.2009-04-11":1705362558,"105.2009-03-14":1705362558,"106.2009-02-13":1705362558,"107.2009-01-10":1705362558,"108.2008-11-06":1705362558,"109.2008-10-11":1705362558,"110.2008-07-12":1705362558},"checksum":"78c3fbd10258f52093d3ed3018d95a64"},"04.reports\/01.2021-09-11":{"key":"reports\/2021-09-11","storage_key":"04.reports\/01.2021-09-11","template":"reports","storage_timestamp":1705362558,"markdown":{"":{"reports":1705362558}},"checksum":"5ca1abd5e222bfb8b3327d39da7dfafd"},"04.reports\/02.2021-06-19":{"key":"reports\/2021-06-19","storage_key":"04.reports\/02.2021-06-19","template":"reports","storage_timestamp":1705362558,"markdown":{"":{"reports":1705362558}},"checksum":"9bfd8d03d4934d9013aab6b998f53a32"},"04.reports\/03.2021-05-08":{"key":"reports\/2021-05-08","storage_key":"04.reports\/03.2021-05-08","template":"reports","storage_timestamp":1705362558,"markdown":{"":{"reports":1705362558}},"checksum":"89bb0bb5e8ed91d5bd7d49928457d155"},"04.reports\/04.2021-04-10":{"key":"reports\/2021-04-10","storage_key":"04.reports\/04.2021-04-10","template":"reports","storage_timestamp":1705362558,"markdown":{"":{"reports":1705362558}},"checksum":"12f4277cd18470f778c44ea2e6dd240e"},"04.reports\/05.2021-03-13":{"key":"reports\/2021-03-13","storage_key":"04.reports\/05.2021-03-13","template":"reports","storage_timestamp":1705362558,"markdown":{"":{"reports":1705362558}},"checksum":"cf101a28af082ef93acd3e6db445e67a"},"04.reports\/06.2021-02-13":{"key":"reports\/2021-02-13","storage_key":"04.reports\/06.2021-02-13","template":"reports","storage_timestamp":1705362558,"markdown":{"":{"reports":1705362558}},"checksum":"526eefa5e67b370bf3c71989bad2c56c"},"04.reports\/07.2021-01-16":{"key":"reports\/2021-01-16","storage_key":"04.reports\/07.2021-01-16","template":"reports","storage_timestamp":1705362558,"markdown":{"":{"reports":1705362558}},"checksum":"86b25cdd2492c0108cbe194dcca70ae9"},"04.reports\/08.2020-02-08":{"key":"reports\/2020-02-08","storage_key":"04.reports\/08.2020-02-08","template":"reports","storage_timestamp":1705362558,"markdown":{"":{"reports":1705362558}},"checksum":"2b149c301b4ab8b2586cc76b5fba1a10"},"04.reports\/09.2020-01-19":{"key":"reports\/2020-01-19","storage_key":"04.reports\/09.2020-01-19","template":"reports","storage_timestamp":1705362558,"markdown":{"":{"reports":1705362558}},"checksum":"f72daa66c40627bf77487c95ab1e14d3"},"04.reports\/10.2019-11-09":{"key":"reports\/2019-11-09","storage_key":"04.reports\/10.2019-11-09","template":"reports","storage_timestamp":1705362558,"markdown":{"":{"reports":1705362558}},"checksum":"c1308ba813b0e73280af4aea8c7cc1cd"},"04.reports\/11.2019-09-14":{"key":"reports\/2019-09-14","storage_key":"04.reports\/11.2019-09-14","template":"reports","storage_timestamp":1705362558,"markdown":{"":{"reports":1705362558}},"checksum":"cb61774f87210d5e720f8b9c1c545aff"},"04.reports\/12.2019-06-08":{"key":"reports\/2019-06-08","storage_key":"04.reports\/12.2019-06-08","template":"reports","storage_timestamp":1705362558,"markdown":{"":{"reports":1705362558}},"checksum":"fc41bbae569b6557855bfb830fb3111e"},"04.reports\/13.2019-05-11":{"key":"reports\/2019-05-11","storage_key":"04.reports\/13.2019-05-11","template":"reports","storage_timestamp":1705362558,"markdown":{"":{"reports":1705362558}},"checksum":"25b3b8d7ebec803cba8a8d6ad08c9fe6"},"04.reports\/14.2019-04-13":{"key":"reports\/2019-04-13","storage_key":"04.reports\/14.2019-04-13","template":"reports","storage_timestamp":1705362558,"markdown":{"":{"reports":1705362558}},"checksum":"74a0dd1626291d55f259168fbfc1d09f"},"04.reports\/15.2019-03-16":{"key":"reports\/2019-03-16","storage_key":"04.reports\/15.2019-03-16","template":"reports","storage_timestamp":1705362558,"markdown":{"":{"reports":1705362558}},"checksum":"ee2c913c505ddd9a156c610867873d35"},"04.reports\/16.2019-02-09":{"key":"reports\/2019-02-09","storage_key":"04.reports\/16.2019-02-09","template":"reports","storage_timestamp":1705362558,"markdown":{"":{"reports":1705362558}},"checksum":"5f90144047f71930be8a7160016363b3"},"04.reports\/17.2019-01-19":{"key":"reports\/2019-01-19","storage_key":"04.reports\/17.2019-01-19","template":"reports","storage_timestamp":1705362558,"markdown":{"":{"reports":1705362558}},"checksum":"1a75e5bdc75cfad9c356ceba2dadce64"},"04.reports\/18.2018-05-12":{"key":"reports\/2018-05-12","storage_key":"04.reports\/18.2018-05-12","template":"reports","storage_timestamp":1705362558,"markdown":{"":{"reports":1705362558}},"checksum":"7710b222043da0bb7797f04d8749913a"},"04.reports\/19.2018-04-14":{"key":"reports\/2018-04-14","storage_key":"04.reports\/19.2018-04-14","template":"reports","storage_timestamp":1705362558,"markdown":{"":{"reports":1705362558}},"checksum":"3d7c63ac1daa89c1d22346fe76b635cb"},"04.reports\/20.2018-02-10":{"key":"reports\/2018-02-10","storage_key":"04.reports\/20.2018-02-10","template":"reports","storage_timestamp":1705362558,"markdown":{"":{"reports":1705362558}},"checksum":"407788cff1019fa27a376882c048348c"},"04.reports\/21.2018-01-13":{"key":"reports\/2018-01-13","storage_key":"04.reports\/21.2018-01-13","template":"reports","storage_timestamp":1705362558,"markdown":{"":{"reports":1705362558}},"checksum":"2207a596f460e60b94d6b50207939b7a"},"04.reports\/22.2018-03-10":{"key":"reports\/2018-03-10","storage_key":"04.reports\/22.2018-03-10","template":"reports","storage_timestamp":1705362558,"markdown":{"":{"reports":1705362558}},"checksum":"8c6671d9e16750086611e168cc16332b"},"04.reports\/23.2017-11-11":{"key":"reports\/2017-11-11","storage_key":"04.reports\/23.2017-11-11","template":"reports","storage_timestamp":1705362558,"markdown":{"":{"reports":1705362558}},"checksum":"1af1e2b7bc4149583a1a76752a275a5f"},"04.reports\/24.2017-10-14":{"key":"reports\/2017-10-14","storage_key":"04.reports\/24.2017-10-14","template":"reports","storage_timestamp":1705362558,"markdown":{"":{"reports":1705362558}},"checksum":"51033e936a9962055202af71bb6b9a39"},"04.reports\/25.2017-09-09":{"key":"reports\/2017-09-09","storage_key":"04.reports\/25.2017-09-09","template":"reports","storage_timestamp":1705362558,"markdown":{"":{"reports":1705362558}},"checksum":"cc8a9a0867a479ba67531662bbd39d7e"},"04.reports\/26.2017-06-10":{"key":"reports\/2017-06-10","storage_key":"04.reports\/26.2017-06-10","template":"reports","storage_timestamp":1705362558,"markdown":{"":{"reports":1705362558}},"checksum":"f3207396eade407605b1c40555b44821"},"04.reports\/27.2017-05-13":{"key":"reports\/2017-05-13","storage_key":"04.reports\/27.2017-05-13","template":"reports","storage_timestamp":1705362558,"markdown":{"":{"reports":1705362558}},"checksum":"b3465ce73a89da01f5f3cf713e4d845d"},"04.reports\/28.2017-04-08":{"key":"reports\/2017-04-08","storage_key":"04.reports\/28.2017-04-08","template":"reports","storage_timestamp":1705362558,"markdown":{"":{"reports":1705362558}},"checksum":"b789616d7d91bfa97557c850e4d8b542"},"04.reports\/29.2017-02-11":{"key":"reports\/2017-02-11","storage_key":"04.reports\/29.2017-02-11","template":"reports","storage_timestamp":1705362558,"markdown":{"":{"reports":1705362558}},"checksum":"5e65568184165293ce1c43a390bd5bca"},"04.reports\/30.2017-01-14":{"key":"reports\/2017-01-14","storage_key":"04.reports\/30.2017-01-14","template":"reports","storage_timestamp":1705362558,"markdown":{"":{"reports":1705362558}},"checksum":"9ee0fc4a7f3d3184f24388ad11a3043c"},"04.reports\/31.2016-11-12":{"key":"reports\/2016-11-12","storage_key":"04.reports\/31.2016-11-12","template":"reports","storage_timestamp":1705362558,"markdown":{"":{"reports":1705362558}},"checksum":"c3c3bdc8ba7b23ff38005b3f97a49cb6"},"04.reports\/32.2016-10-08":{"key":"reports\/2016-10-08","storage_key":"04.reports\/32.2016-10-08","template":"reports","storage_timestamp":1705362558,"markdown":{"":{"reports":1705362558}},"checksum":"bf9dfb16397fdfc0e90e73ccad4db7d0"},"04.reports\/33.2016-09-10":{"key":"reports\/2016-09-10","storage_key":"04.reports\/33.2016-09-10","template":"reports","storage_timestamp":1705362558,"markdown":{"":{"reports":1705362558}},"checksum":"2965a40580d544c632cb64afa52c11c3"},"04.reports\/34.2016-06-11":{"key":"reports\/2016-06-11","storage_key":"04.reports\/34.2016-06-11","template":"reports","storage_timestamp":1705362558,"markdown":{"":{"reports":1705362558}},"checksum":"ab5a0547ccc23315547030747e3f365f"},"04.reports\/35.2016-05-14":{"key":"reports\/2016-05-14","storage_key":"04.reports\/35.2016-05-14","template":"reports","storage_timestamp":1705362558,"markdown":{"":{"reports":1705362558}},"checksum":"23414508ed7b49b7dd38d4cf0fd927f1"},"04.reports\/36.2016-04-09":{"key":"reports\/2016-04-09","storage_key":"04.reports\/36.2016-04-09","template":"reports","storage_timestamp":1705362558,"markdown":{"":{"reports":1705362558}},"checksum":"0b3a367e5b358a22670a60d22643a3b1"},"04.reports\/37.2016-03-12":{"key":"reports\/2016-03-12","storage_key":"04.reports\/37.2016-03-12","template":"reports","storage_timestamp":1705362558,"markdown":{"":{"reports":1705362558}},"checksum":"057abb15cbadee6d460ddb1b9d79b688"},"04.reports\/38.2016-02-13":{"key":"reports\/2016-02-13","storage_key":"04.reports\/38.2016-02-13","template":"reports","storage_timestamp":1705362558,"markdown":{"":{"reports":1705362558}},"checksum":"abdc205d700b38a55259d9e96e75ae1a"},"04.reports\/39.2016-01-09":{"key":"reports\/2016-01-09","storage_key":"04.reports\/39.2016-01-09","template":"reports","storage_timestamp":1705362558,"markdown":{"":{"reports":1705362558}},"checksum":"fddcb09b91aca664405ac666d827581d"},"04.reports\/40.2015-11-14":{"key":"reports\/2015-11-14","storage_key":"04.reports\/40.2015-11-14","template":"reports","storage_timestamp":1705362558,"markdown":{"":{"reports":1705362558}},"checksum":"a3c6f4abf79fd7ad1c14bfd3a3618999"},"04.reports\/41.2015-10-10":{"key":"reports\/2015-10-10","storage_key":"04.reports\/41.2015-10-10","template":"reports","storage_timestamp":1705362558,"markdown":{"":{"reports":1705362558}},"checksum":"dcaaaece6d26749c542db33820270457"},"04.reports\/42.2015-09-12":{"key":"reports\/2015-09-12","storage_key":"04.reports\/42.2015-09-12","template":"reports","storage_timestamp":1705362558,"markdown":{"":{"reports":1705362558}},"checksum":"67628ba989ee896adad568f103c17416"},"04.reports\/43.2015-06-13":{"key":"reports\/2015-06-13","storage_key":"04.reports\/43.2015-06-13","template":"reports","storage_timestamp":1705362558,"markdown":{"":{"reports":1705362558}},"checksum":"4d50f99d4e298616a481f167de4f4830"},"04.reports\/44.2015-05-09":{"key":"reports\/2015-05-09","storage_key":"04.reports\/44.2015-05-09","template":"reports","storage_timestamp":1705362558,"markdown":{"":{"reports":1705362558}},"checksum":"943efc02537cf19a23e2b7705927d337"},"04.reports\/45.2015-04-11":{"key":"reports\/2015-04-11","storage_key":"04.reports\/45.2015-04-11","template":"reports","storage_timestamp":1705362558,"markdown":{"":{"reports":1705362558}},"checksum":"9c58afc97ef87b8c6bc70fb25433d9e8"},"04.reports\/46.2015-03-14":{"key":"reports\/2015-03-14","storage_key":"04.reports\/46.2015-03-14","template":"reports","storage_timestamp":1705362558,"markdown":{"":{"reports":1705362558}},"checksum":"224894fc3fa132d4b102918e6e83b184"},"04.reports\/47.2015-02-14":{"key":"reports\/2015-02-14","storage_key":"04.reports\/47.2015-02-14","template":"reports","storage_timestamp":1705362558,"markdown":{"":{"reports":1705362558}},"checksum":"45f89250e7cc103e40b69e1fe24bb0be"},"04.reports\/48.2015-01-10":{"key":"reports\/2015-01-10","storage_key":"04.reports\/48.2015-01-10","template":"reports","storage_timestamp":1705362558,"markdown":{"":{"reports":1705362558}},"checksum":"17f87d852c6e8f6c43a609eb2399e5bf"},"04.reports\/49.2014-11-08":{"key":"reports\/2014-11-08","storage_key":"04.reports\/49.2014-11-08","template":"reports","storage_timestamp":1705362558,"markdown":{"":{"reports":1705362558}},"checksum":"8751b66512a6e736dc42d08b5f07df4f"},"04.reports\/50.2014-10-11":{"key":"reports\/2014-10-11","storage_key":"04.reports\/50.2014-10-11","template":"reports","storage_timestamp":1705362558,"markdown":{"":{"reports":1705362558}},"checksum":"85518e63de1a00277dffbc6acecaf8a9"},"04.reports\/51.2014-09-13":{"key":"reports\/2014-09-13","storage_key":"04.reports\/51.2014-09-13","template":"reports","storage_timestamp":1705362558,"markdown":{"":{"reports":1705362558}},"checksum":"11b9f3593081a6c6c1b454c703a02c73"},"04.reports\/52.2014-07-19":{"key":"reports\/2014-07-19","storage_key":"04.reports\/52.2014-07-19","template":"reports","storage_timestamp":1705362558,"markdown":{"":{"reports":1705362558}},"checksum":"e8a991ddb12cbe684d2ee111777fc1fc"},"04.reports\/53.2014-06-14":{"key":"reports\/2014-06-14","storage_key":"04.reports\/53.2014-06-14","template":"reports","storage_timestamp":1705362558,"markdown":{"":{"reports":1705362558}},"checksum":"ed388e036a6cf8d17e383a816665099d"},"04.reports\/54.2014-05-24":{"key":"reports\/2014-05-24","storage_key":"04.reports\/54.2014-05-24","template":"reports","storage_timestamp":1705362558,"markdown":{"":{"reports":1705362558}},"checksum":"83036d7c8ea21b8d58eafe0c361d2baf"},"04.reports\/55.2014-03-08":{"key":"reports\/2014-03-08","storage_key":"04.reports\/55.2014-03-08","template":"reports","storage_timestamp":1705362558,"markdown":{"":{"reports":1705362558}},"checksum":"9281ecea1350b1159e4e5b4c237bfdae"},"04.reports\/56.2014-01-11":{"key":"reports\/2014-01-11","storage_key":"04.reports\/56.2014-01-11","template":"reports","storage_timestamp":1705362558,"markdown":{"":{"reports":1705362558}},"checksum":"5f4a130990ebedc9db2f4e57d03de711"},"04.reports\/57.2013-09-14":{"key":"reports\/2013-09-14","storage_key":"04.reports\/57.2013-09-14","template":"reports","storage_timestamp":1705362558,"markdown":{"":{"reports":1705362558}},"checksum":"8cddccbe708d82e748718bcbd4f6238e"},"04.reports\/58.2013-05-11":{"key":"reports\/2013-05-11","storage_key":"04.reports\/58.2013-05-11","template":"reports","storage_timestamp":1705362558,"markdown":{"":{"reports":1705362558}},"checksum":"df2f9088e71fea8133db16da345af4cb"},"04.reports\/59.2013-06-08":{"key":"reports\/2013-06-08","storage_key":"04.reports\/59.2013-06-08","template":"reports","storage_timestamp":1705362558,"markdown":{"":{"reports":1705362558}},"checksum":"b39370286e18fb2c60da93049d910f7d"},"04.reports\/60.2013-04-13":{"key":"reports\/2013-04-13","storage_key":"04.reports\/60.2013-04-13","template":"reports","storage_timestamp":1705362558,"markdown":{"":{"reports":1705362558}},"checksum":"d6c169e6cc67c988912c7b38f65f0d51"},"04.reports\/61.2013-03-09":{"key":"reports\/2013-03-09","storage_key":"04.reports\/61.2013-03-09","template":"reports","storage_timestamp":1705362558,"markdown":{"":{"reports":1705362558}},"checksum":"4073b16a5dc58a16a2031bd8e5d82d53"},"04.reports\/62.2013-02-09":{"key":"reports\/2013-02-09","storage_key":"04.reports\/62.2013-02-09","template":"reports","storage_timestamp":1705362558,"markdown":{"":{"reports":1705362558}},"checksum":"578d3e3f213be4bb47b57a50e88e09a7"},"04.reports\/63.2013-01-12":{"key":"reports\/2013-01-12","storage_key":"04.reports\/63.2013-01-12","template":"reports","storage_timestamp":1705362558,"markdown":{"":{"reports":1705362558}},"checksum":"29f993ec25a86e66c2661c50c5e335c5"},"04.reports\/64.2012-11-10":{"key":"reports\/2012-11-10","storage_key":"04.reports\/64.2012-11-10","template":"reports","storage_timestamp":1705362558,"markdown":{"":{"reports":1705362558}},"checksum":"ac480bdabe6c3e2b3c9c920c76bf3337"},"04.reports\/65.2012-10-06":{"key":"reports\/2012-10-06","storage_key":"04.reports\/65.2012-10-06","template":"reports","storage_timestamp":1705362558,"markdown":{"":{"reports":1705362558}},"checksum":"ed78bcc6cfd6d5adadf5d8a81dc6cafc"},"04.reports\/66.2012-09-08":{"key":"reports\/2012-09-08","storage_key":"04.reports\/66.2012-09-08","template":"reports","storage_timestamp":1705362558,"markdown":{"":{"reports":1705362558}},"checksum":"dbd220ec86719a308eb5011f94132693"},"04.reports\/67.2012-07-14":{"key":"reports\/2012-07-14","storage_key":"04.reports\/67.2012-07-14","template":"reports","storage_timestamp":1705362558,"markdown":{"":{"reports":1705362558}},"checksum":"1f7c2dd00eeb802274f5418152d17fca"},"04.reports\/68.2012-06-09":{"key":"reports\/2012-06-09","storage_key":"04.reports\/68.2012-06-09","template":"reports","storage_timestamp":1705362558,"markdown":{"":{"reports":1705362558}},"checksum":"e99a922047d647e15524b5ca3ecfb18e"},"04.reports\/69.2012-05-12":{"key":"reports\/2012-05-12","storage_key":"04.reports\/69.2012-05-12","template":"reports","storage_timestamp":1705362558,"markdown":{"":{"reports":1705362558}},"checksum":"3554eb45a668ceb991ce208de06b9510"},"04.reports\/70.2012-04-14":{"key":"reports\/2012-04-14","storage_key":"04.reports\/70.2012-04-14","template":"reports","storage_timestamp":1705362558,"markdown":{"":{"reports":1705362558}},"checksum":"e1248e38bbc2675191b8fe891099d2b3"},"04.reports\/71.2012-03-10":{"key":"reports\/2012-03-10","storage_key":"04.reports\/71.2012-03-10","template":"reports","storage_timestamp":1705362558,"markdown":{"":{"reports":1705362558}},"checksum":"82e7af0fa7f4bd59da9e4dc64c089d13"},"04.reports\/72.2012-02-11":{"key":"reports\/2012-02-11","storage_key":"04.reports\/72.2012-02-11","template":"reports","storage_timestamp":1705362558,"markdown":{"":{"reports":1705362558}},"checksum":"ee7532b5488aae12ae76e14770f0b1fe"},"04.reports\/73.2012-01-14":{"key":"reports\/2012-01-14","storage_key":"04.reports\/73.2012-01-14","template":"reports","storage_timestamp":1705362558,"markdown":{"":{"reports":1705362558}},"checksum":"4b16445479a3fff63fe94b3488264fea"},"04.reports\/74.2011-11-26":{"key":"reports\/2011-11-26","storage_key":"04.reports\/74.2011-11-26","template":"reports","storage_timestamp":1705362558,"markdown":{"":{"reports":1705362558}},"checksum":"10325dde4e2c65c30903e8541142ecbb"},"04.reports\/75.2011-11-12":{"key":"reports\/2011-11-12","storage_key":"04.reports\/75.2011-11-12","template":"reports","storage_timestamp":1705362558,"markdown":{"":{"reports":1705362558}},"checksum":"ab54ba5bfa5697a9616d8b766cf18997"},"04.reports\/76.2011-10-08":{"key":"reports\/2011-10-08","storage_key":"04.reports\/76.2011-10-08","template":"reports","storage_timestamp":1705362558,"markdown":{"":{"reports":1705362558}},"checksum":"d271cc0ba7c2ea7a0ddc3431ec649275"},"04.reports\/77.2011-09-10":{"key":"reports\/2011-09-10","storage_key":"04.reports\/77.2011-09-10","template":"reports","storage_timestamp":1705362558,"markdown":{"":{"reports":1705362558}},"checksum":"8af602a5108a30853a5ab30f95d0e4a7"},"04.reports\/78.2011-09-03":{"key":"reports\/2011-09-03","storage_key":"04.reports\/78.2011-09-03","template":"reports","storage_timestamp":1705362558,"markdown":{"":{"reports":1705362558}},"checksum":"013c79fd54fb6732512bb428a4743d89"},"04.reports\/79.2011-07-09":{"key":"reports\/2011-07-09","storage_key":"04.reports\/79.2011-07-09","template":"reports","storage_timestamp":1705362558,"markdown":{"":{"reports":1705362558}},"checksum":"6978a3a890b3a9c6758b00df2d3bace4"},"04.reports\/80.2011-06-11":{"key":"reports\/2011-06-11","storage_key":"04.reports\/80.2011-06-11","template":"reports","storage_timestamp":1705362558,"markdown":{"":{"reports":1705362558}},"checksum":"9ac023ea77010bc1ff3b8691a5e8e3bf"},"04.reports\/81.2011-05-14":{"key":"reports\/2011-05-14","storage_key":"04.reports\/81.2011-05-14","template":"reports","storage_timestamp":1705362558,"markdown":{"":{"reports":1705362558}},"checksum":"7248a10604208e70ee2cb4fdd548bd9c"},"04.reports\/82.2011-04-09":{"key":"reports\/2011-04-09","storage_key":"04.reports\/82.2011-04-09","template":"reports","storage_timestamp":1705362558,"markdown":{"":{"reports":1705362558}},"checksum":"869a0a26caf4855bc2cfcb510a187f1e"},"04.reports\/83.2011-03-12":{"key":"reports\/2011-03-12","storage_key":"04.reports\/83.2011-03-12","template":"reports","storage_timestamp":1705362558,"markdown":{"":{"reports":1705362558}},"checksum":"35ee323802a7fe902ff390cb9a61b0c0"},"04.reports\/84.2011-02-12":{"key":"reports\/2011-02-12","storage_key":"04.reports\/84.2011-02-12","template":"reports","storage_timestamp":1705362558,"markdown":{"":{"reports":1705362558}},"checksum":"9d309ce62f8ca4596261df8a5ccdc71c"},"04.reports\/85.2011-01-08":{"key":"reports\/2011-01-08","storage_key":"04.reports\/85.2011-01-08","template":"reports","storage_timestamp":1705362558,"markdown":{"":{"reports":1705362558}},"checksum":"59b4e50547b000f8fe7a1b16d1d1adec"},"04.reports\/86.2010-11-13":{"key":"reports\/2010-11-13","storage_key":"04.reports\/86.2010-11-13","template":"reports","storage_timestamp":1705362558,"markdown":{"":{"reports":1705362558}},"checksum":"531848fcca61f643de94f568a7fdcc32"},"04.reports\/87.2010-10-09":{"key":"reports\/2010-10-09","storage_key":"04.reports\/87.2010-10-09","template":"reports","storage_timestamp":1705362558,"markdown":{"":{"reports":1705362558}},"checksum":"9c727e997402b78ffe63da63e6861761"},"04.reports\/88.2010-09-23":{"key":"reports\/2010-09-23","storage_key":"04.reports\/88.2010-09-23","template":"reports","storage_timestamp":1705362558,"markdown":{"":{"reports":1705362558}},"checksum":"9739f508d0e45daf116fa58f804e16b0"},"04.reports\/89.2010-09-11":{"key":"reports\/2010-09-11","storage_key":"04.reports\/89.2010-09-11","template":"reports","storage_timestamp":1705362558,"markdown":{"":{"reports":1705362558}},"checksum":"73970efd5c12bd935148c5d68b8f6eba"},"04.reports\/90.2010-07-10":{"key":"reports\/2010-07-10","storage_key":"04.reports\/90.2010-07-10","template":"reports","storage_timestamp":1705362558,"markdown":{"":{"reports":1705362558}},"checksum":"ab04ad0d10118dac839b109537feb185"},"04.reports\/91.2010-06-12":{"key":"reports\/2010-06-12","storage_key":"04.reports\/91.2010-06-12","template":"reports","storage_timestamp":1705362558,"markdown":{"":{"reports":1705362558}},"checksum":"a0609a24055014ba5e82f6290ce5c8a1"},"04.reports\/92.2010-05-08":{"key":"reports\/2010-05-08","storage_key":"04.reports\/92.2010-05-08","template":"reports","storage_timestamp":1705362558,"markdown":{"":{"reports":1705362558}},"checksum":"b077a15c7fabd5b113122dda4fdd50d8"},"04.reports\/93.2010-04-10":{"key":"reports\/2010-04-10","storage_key":"04.reports\/93.2010-04-10","template":"reports","storage_timestamp":1705362558,"markdown":{"":{"reports":1705362558}},"checksum":"6a80dffa83cb3b721f7a29b335821154"},"04.reports\/94.2010-03-13":{"key":"reports\/2010-03-13","storage_key":"04.reports\/94.2010-03-13","template":"reports","storage_timestamp":1705362558,"markdown":{"":{"reports":1705362558}},"checksum":"0a15cd77084d138f6bf3e7ac3d544756"},"04.reports\/95.2010-02-13":{"key":"reports\/2010-02-13","storage_key":"04.reports\/95.2010-02-13","template":"reports","storage_timestamp":1705362558,"markdown":{"":{"reports":1705362558}},"checksum":"6e6efd036680fdd27147e9dd5a07b659"},"04.reports\/96.2010-01-09":{"key":"reports\/2010-01-09","storage_key":"04.reports\/96.2010-01-09","template":"reports","storage_timestamp":1705362558,"markdown":{"":{"reports":1705362558}},"checksum":"c75fae4867979491d151403e605af05a"},"04.reports\/97.2009-11-19":{"key":"reports\/2009-11-19","storage_key":"04.reports\/97.2009-11-19","template":"reports","storage_timestamp":1705362558,"markdown":{"":{"reports":1705362558}},"checksum":"8657aee684fab4dd61d461917e7c37eb"},"04.reports\/98.2009-11-15":{"key":"reports\/2009-11-15","storage_key":"04.reports\/98.2009-11-15","template":"reports","storage_timestamp":1705362558,"markdown":{"":{"reports":1705362558}},"checksum":"f1bc9a311eb3fad8318f5c63e094596c"},"04.reports\/99.2009-10-10":{"key":"reports\/2009-10-10","storage_key":"04.reports\/99.2009-10-10","template":"reports","storage_timestamp":1705362558,"markdown":{"":{"reports":1705362558}},"checksum":"74308d9cb640e5a7ecbadb6927c4c5bb"},"04.reports\/100.2009-09-26":{"key":"reports\/2009-09-26","storage_key":"04.reports\/100.2009-09-26","template":"reports","storage_timestamp":1705362558,"markdown":{"":{"reports":1705362558}},"checksum":"95593913c3f56c08e8d212e1c5a61ef4"},"04.reports\/101.2009-07-11":{"key":"reports\/2009-07-11","storage_key":"04.reports\/101.2009-07-11","template":"reports","storage_timestamp":1705362558,"markdown":{"":{"reports":1705362558}},"checksum":"c0913921e77b48c7f4f64d8e34234b76"},"04.reports\/102.2009-06-13":{"key":"reports\/2009-06-13","storage_key":"04.reports\/102.2009-06-13","template":"reports","storage_timestamp":1705362558,"markdown":{"":{"reports":1705362558}},"checksum":"ee9f44386407ffb18e8dbb19880d4a10"},"04.reports\/103.2009-05-09":{"key":"reports\/2009-05-09","storage_key":"04.reports\/103.2009-05-09","template":"reports","storage_timestamp":1705362558,"markdown":{"":{"reports":1705362558}},"checksum":"79743becd43e99c1d1b05088179d7a7a"},"04.reports\/104.2009-04-11":{"key":"reports\/2009-04-11","storage_key":"04.reports\/104.2009-04-11","template":"reports","storage_timestamp":1705362558,"markdown":{"":{"reports":1705362558}},"checksum":"a458b0e5b2e5ab751238713f3b536d8a"},"04.reports\/105.2009-03-14":{"key":"reports\/2009-03-14","storage_key":"04.reports\/105.2009-03-14","template":"reports","storage_timestamp":1705362558,"markdown":{"":{"reports":1705362558}},"checksum":"ce7132781b1317c8f05d6c4d7bbd39ca"},"04.reports\/106.2009-02-13":{"key":"reports\/2009-02-13","storage_key":"04.reports\/106.2009-02-13","template":"reports","storage_timestamp":1705362558,"markdown":{"":{"reports":1705362558}},"checksum":"a0425c0dfbf70a94299df7f70e6b4078"},"04.reports\/107.2009-01-10":{"key":"reports\/2009-01-10","storage_key":"04.reports\/107.2009-01-10","template":"reports","storage_timestamp":1705362558,"markdown":{"":{"reports":1705362558}},"checksum":"eb000c542dde885d93a554577998b39e"},"04.reports\/108.2008-11-06":{"key":"reports\/2008-11-06","storage_key":"04.reports\/108.2008-11-06","template":"reports","storage_timestamp":1705362558,"markdown":{"":{"reports":1705362558}},"checksum":"8a972487e267489ddb908014090f68e8"},"04.reports\/109.2008-10-11":{"key":"reports\/2008-10-11","storage_key":"04.reports\/109.2008-10-11","template":"reports","storage_timestamp":1705362558,"markdown":{"":{"reports":1705362558}},"checksum":"41617d631339bd26a09830a1a982d359"},"04.reports\/110.2008-07-12":{"key":"reports\/2008-07-12","storage_key":"04.reports\/110.2008-07-12","template":"reports","storage_timestamp":1705362558,"markdown":{"":{"reports":1705362558}},"checksum":"3c42e74dbb890d19d6994dc8e60450cd"},"05.information":{"key":"information","storage_key":"05.information","template":"default","storage_timestamp":1705362558,"markdown":{"":{"default":1705362558}},"checksum":"e0f1fc8eb4490d653716d5075224ab25"},"06.location":{"key":"location","storage_key":"06.location","template":"default","storage_timestamp":1705362558,"markdown":{"":{"default":1705362558}},"checksum":"88cd2b8425bffd8d836ae140604a05b3"},"07.joining":{"key":"joining","storage_key":"07.joining","template":"default","storage_timestamp":1705362558,"markdown":{"":{"default":1705362558}},"checksum":"4106e3ca1d7e058cac1d0da8db95c307"},"08.constitution":{"key":"constitution","storage_key":"08.constitution","template":"default","storage_timestamp":1705362558,"markdown":{"":{"default":1705362558}},"checksum":"59897611e37aa30320908a8033965f58"},"content":{"key":"content","storage_key":"content","template":null,"storage_timestamp":1705362558,"children":{"08.special-event-in-june-2018":1705362558,"09.2024-chapter-officer-positions":1705362558,"10.chapter-officers-for-2018":1705362558},"checksum":"2b4d4d584e14cb3e550a9307274a29af"},"content\/08.special-event-in-june-2018":{"key":"content\/special-event-in-june-2018","storage_key":"content\/08.special-event-in-june-2018","template":"default","storage_timestamp":1705362558,"markdown":{"":{"default":1705362558}},"checksum":"53a5476e5552f8538efae229d8142121"},"content\/09.2024-chapter-officer-positions":{"key":"content\/2024-chapter-officer-positions","storage_key":"content\/09.2024-chapter-officer-positions","template":"default","storage_timestamp":1705362558,"markdown":{"":{"default":1705362558}},"checksum":"6b03f7c51ed744dc6942bf53c2449731"},"content\/10.chapter-officers-for-2018":{"key":"content\/chapter-officers-for-2018","storage_key":"content\/10.chapter-officers-for-2018","template":"default","storage_timestamp":1705362558,"markdown":{"":{"default":1705362558}},"checksum":"5ec00db07d94548b95f1c12382dc55b8"},"search":{"key":"search","storage_key":"search","template":"simplesearch_results","storage_timestamp":1705362558,"markdown":{"":{"simplesearch_results":1705362558}},"checksum":"be644c6b3f20b7957f05dd0c512e53c5"}}}